[
  {
    "message": "我感到一阵眩目，醒了过来。"
  },
  {
    "message": "结果还是几乎没睡着……。\r\n全身都有一种倦怠感。"
  },
  {
    "message": "……灯理已经起床了吗？"
  },
  {
    "message": "我翻了个身，想看看灯理的脸。"
  },
  {
    "name": "灯理",
    "message": "「哥哥，早上好」"
  },
  {
    "message": "灯理的脸一出现在视野里，\r\n我们的视线就对上了。"
  },
  {
    "name": "凪",
    "message": "「早，早上好。你已经起床啦……起得真早」"
  },
  {
    "name": "灯理",
    "message": "「嗯～其实是因为心跳得太快了，\r\n所以才睡不着的」"
  },
  {
    "name": "凪",
    "message": "「明明是你先说想跟我一起睡的，\r\n那不就没意义了吗」"
  },
  {
    "name": "灯理",
    "message": "「很有意义哦～」"
  },
  {
    "name": "灯理",
    "message": "「因为我想和哥哥一起睡，\r\n想消除掉不安的心情嘛」"
  },
  {
    "name": "灯理",
    "message": "「虽然因为哥哥的吻而睡不着，\r\n但心情却很舒畅」"
  },
  {
    "name": "灯理",
    "message": "「哥哥睡得好吗？」"
  },
  {
    "name": "凪",
    "message": "「実を言うと俺もあまり眠れてなかったり」"
  },
  {
    "name": "灯理",
    "message": "「难道哥哥也心跳加速\r\n睡不着吗？」"
  },
  {
    "name": "凪",
    "message": "「就算不问也知道吧」"
  },
  {
    "name": "灯理",
    "message": "「人家想听哥哥亲口说出来啦～。\r\n呐～，快说嘛～」"
  },
  {
    "name": "凪",
    "message": "「……嗯，是啊。灯理害我睡不着了」"
  },
  {
    "name": "灯理",
    "message": "「灯理好开心～。哥哥，你终于肯说出来了呢～」"
  },
  {
    "name": "灯理",
    "message": "「哥哥，你听我说。\r\n这下子，你明白了吧？」"
  },
  {
    "name": "凪",
    "message": "「你指的是？」"
  },
  {
    "name": "灯理",
    "message": "「从今天开始，我就是哥哥的未婚妻了」"
  },
  {
    "name": "灯理",
    "message": "「因为，哥哥心中最重要的女孩子\r\n不就是我吗？　都接吻过了……」"
  },
  {
    "name": "凪",
    "message": "「啊啊，关于那个……」"
  },
  {
    "name": "灯理",
    "message": "「嗯」"
  },
  {
    "name": "凪",
    "message": "「我们先来个恋人期间吧。\r\n如果没问题的话，我会再向你告白的」"
  },
  {
    "name": "灯理",
    "message": "「那个……这和未婚妻有什么区别吗？\r\n未婚妻不也差不多吗？」"
  },
  {
    "name": "凪",
    "message": "「话是这么说，但我还不知道\r\n自己对恋人会采取怎样的态度」"
  },
  {
    "name": "凪",
    "message": "「如果我是个坏男人的话，就不要和我约定\r\n什么结婚，赶紧分手比较好」"
  },
  {
    "name": "灯理",
    "message": "「哥哥，哥哥，等等？\r\n只要哥哥注意一下就行了对吧？」"
  },
  {
    "name": "凪",
    "message": "「虽然对灯理不太好意思，但我可不像灯理那样\r\n信任我自己。希望你能再观察一下」"
  },
  {
    "name": "凪",
    "message": "「如果不行的话就甩了我吧。\r\n我不想看到灯理伤心的样子」"
  },
  {
    "name": "灯理",
    "message": "「哥哥太重视我了啦」"
  },
  {
    "name": "凪",
    "message": "「不愿意吗？」"
  },
  {
    "name": "灯理",
    "message": "「怎么会不愿意呢。不如说我很开心……\r\n我觉得顺从自己的想法和冲动也是很重要的」"
  },
  {
    "name": "凪",
    "message": "「顺从自己的想法和冲动……」"
  },
  {
    "name": "凪",
    "message": "「然后让玖玖瑠说『我监禁了灯理』的谎话\r\n让我和你起争执的，又是谁呢？」"
  },
  {
    "name": "灯理",
    "message": "「唔，唔唔唔……那个……\r\n我知道了……恋人期间，可以吗……」"
  },
  {
    "name": "凪",
    "message": "「好，就这么定了。那差不多该起床了」"
  },
  {
    "name": "灯理",
    "message": "「在那之前……。我还想要个早安吻」"
  },
  {
    "name": "凪",
    "message": "「哎，又来了？」"
  },
  {
    "name": "灯理",
    "message": "「哦哦。哥哥心动的表情。\r\n好新鲜啊～。呵呵呵」"
  },
  {
    "name": "凪",
    "message": "「哎呀，别一直盯着看！」"
  },
  {
    "name": "凪",
    "message": "「话说你刚才不是说\r\n光是接吻就睡不着了吗？」"
  },
  {
    "name": "灯理",
    "message": "「没事的。\r\n今天我感觉能把那份羞耻心转化为力量」"
  },
  {
    "name": "灯理",
    "message": "「哥哥，你已经不想再和我接吻了吗？」"
  },
  {
    "name": "凪",
    "message": "「我当然想啊……」"
  },
  {
    "name": "灯理",
    "message": "「那就好。来，嗯～」"
  },
  {
    "message": "我明明拼命保持平常心，这家伙却……。\r\n话虽如此，灯理主动索求我，我还是很高兴的。"
  },
  {
    "name": "灯理",
    "message": "「嗯……嗯，啾……哈啊……\r\n一大早就心跳加速，睡不着了」"
  },
  {
    "name": "凪",
    "message": "「我也是……」"
  },
  {
    "name": "灯理",
    "message": "「嗯，呼……嗯嗯……啾，啾……」"
  },
  {
    "message": "明明只是早安的吻，只亲一次就够了，\r\n但灯理的嘴唇太柔软了，我停不下来。"
  },
  {
    "name": "灯理",
    "message": "「哈啊……嗯……啊，哥哥」"
  },
  {
    "message": "我正想进一步深吻，却被灯理阻止了。"
  },
  {
    "name": "凪",
    "message": "「怎，怎么了？　你不喜欢这样吗？」"
  },
  {
    "name": "灯理",
    "message": "「不是啦～，你看看时钟」"
  },
  {
    "name": "凪",
    "message": "「啊……对哦。\r\n差不多该准备了，不然会迟到的」"
  },
  {
    "name": "灯理",
    "message": "「啊……对哦。\r\n得好好去上课才行，今天也加油吧」"
  },
  {
    "name": "凪",
    "message": "「……是啊」"
  },
  {
    "message": "刚才的接吻让我再次确认了。\r\n我果然还是无法相信自己！"
  },
  {
    "message": "要是成为未婚妻的话，我可能就会一下子失去控制。\r\n得小心行动才行。"
  },
  {
    "name": "凪",
    "message": "「那我回房间了」"
  },
  {
    "name": "灯理",
    "message": "「啊，等一下哥哥」"
  },
  {
    "message": "我刚起身准备走出房间，\r\n灯理就用手搭在我的肩上，踮起脚尖。"
  },
  {
    "message": "脸颊上，嘴唇的柔软触感。"
  },
  {
    "name": "灯理",
    "message": "「啾……。\r\n诶嘿嘿，我也想亲哥哥」"
  },
  {
    "name": "灯理",
    "message": "「路上小心，哥哥」"
  },
  {
    "message": "多亏昨天和她聊了很多，\r\n她似乎已经不再感到不安了。"
  },
  {
    "message": "我摸了摸灯理的头，作为回敬她昨天的突袭，\r\n然后回到了自己的房间。"
  },
  {
    "message": "或许是因为承认了对灯理的感情吧，\r\n今天上课时比平时更加集中精神了。"
  },
  {
    "message": "明明还有好多事没做，\r\n回过神来已经到了午休时间。"
  },
  {
    "message": "为了向灯理报告和她交往的事，我邀请了帝雄一起吃午饭。"
  },
  {
    "name": "凪",
    "message": "「帝雄，我有件事想和你说……」"
  },
  {
    "name": "帝雄",
    "message": "「是公司的事？还是社团活动的事？」"
  },
  {
    "name": "凪",
    "message": "「抱歉，不是那些，是关于灯理的。\r\n从今天开始我们就是恋人了」"
  },
  {
    "name": "帝雄",
    "message": "「哦，哦哦……恭喜。\r\n这样可以吧？」"
  },
  {
    "name": "凪",
    "message": "「暂时先这样吧」"
  },
  {
    "name": "帝雄",
    "message": "「但是，你之前不是在找老婆人选吗？\r\n为什么会变成恋人？」"
  },
  {
    "name": "凪",
    "message": "「啊啊，灯理也说了同样的话」"
  },
  {
    "name": "凪",
    "message": "「啊，灯理她也说了同样的话呢\r\n就算订了婚，也还是会有不同的地方吧？」"
  },
  {
    "name": "凪",
    "message": "「所以要慎重，首先从恋人做起……\r\n诶，阿泰？　你笑什么啊」"
  },
  {
    "name": "帝雄",
    "message": "「凪君你真的很喜欢灯理同学呢」"
  },
  {
    "name": "凪",
    "message": "「看起来是这样吗？」"
  },
  {
    "name": "帝雄",
    "message": "「嗯。总是想着灯理同学。\r\n能被这么思念着，灯理同学一定很幸福吧」"
  },
  {
    "name": "凪",
    "message": "「被你这么一说，心情好复杂啊。\r\n我有那么好懂吗……」"
  },
  {
    "name": "伊舞",
    "message": "「是啊，\r\n凪君你真的很好懂呢」"
  },
  {
    "name": "凪",
    "message": "「伊舞！？　你什么时候……」"
  },
  {
    "name": "伊舞",
    "message": "「其实从一开始我就在附近了。\r\n啊，我不是跟踪狂哦？」"
  },
  {
    "name": "伊舞",
    "message": "「我有事要找这个班的学生。\r\n处理完那边的事后，就听到了你们的对话」"
  },
  {
    "name": "帝雄",
    "message": "「…………」"
  },
  {
    "name": "伊舞",
    "message": "「成宫同学，你不用露出那种表情。\r\n我已经彻底斩断对凪的留恋了」"
  },
  {
    "name": "伊舞",
    "message": "「我早就知道会变成这样了」"
  },
  {
    "name": "凪",
    "message": "「诶，是吗？」"
  },
  {
    "name": "伊舞",
    "message": "「我不是说过我对观察力很有自信吗？\r\n凪同学无论何时何地都是灯理，灯理」"
  },
  {
    "name": "帝雄",
    "message": "「确实。\r\n就算我们人多，也总是最先叫灯理的名字」"
  },
  {
    "name": "伊舞",
    "message": "「对吧」"
  },
  {
    "name": "凪",
    "message": "「诶，是这样吗！？」"
  },
  {
    "name": "伊舞",
    "message": "「然后，他们自己都没察觉到。\r\n在这种状态下拖拖拉拉的，对吧？」"
  },
  {
    "name": "凪",
    "message": "「抱，抱歉……」"
  },
  {
    "name": "伊舞",
    "message": "「就算你道歉也没用啊～，虽然先告白的是我，\r\n但拒绝的人也是我」"
  },
  {
    "name": "帝雄",
    "message": "「是吗？」"
  },
  {
    "name": "伊舞",
    "message": "「是的，发生了很多事。所以……」"
  },
  {
    "name": "伊舞",
    "message": "「凪同学被两个美少女夹在中间，犹豫不决，\r\n结果被等不及答案的我甩了」"
  },
  {
    "name": "伊舞",
    "message": "「以上就是我的理解」"
  },
  {
    "name": "伊舞",
    "message": "「不过，感觉进展得有点快呢。\r\n灯理意外地会使用进攻型的战法吗？」"
  },
  {
    "name": "凪",
    "message": "「这种事别问我，去问灯理吧」"
  },
  {
    "name": "伊舞",
    "message": "「切～，那我就去找灯理聊一聊吧～」"
  },
  {
    "message": "说完，伊舞就离开了教室。"
  },
  {
    "name": "凪",
    "message": "「咦，她确实很关心我啊」"
  },
  {
    "name": "帝雄",
    "message": "「或许她就是通过这种方式来\r\n说服自己接受的吧」"
  },
  {
    "name": "帝雄",
    "message": "「不过这也是蓼科同学选择的道路。\r\n我想凪君你不用感到内疚的」"
  },
  {
    "name": "凪",
    "message": "「我的朋友都是些好家伙啊」"
  },
  {
    "name": "帝雄",
    "message": "「这不就是凪君你人品好才有的结果吗」"
  },
  {
    "name": "帝雄",
    "message": "「啊，对了对了，差点忘了说。\r\n今天社团活动好像要休息一天」"
  },
  {
    "name": "凪",
    "message": "「是之前说的电脑维修吗？」"
  },
  {
    "name": "帝雄",
    "message": "「嗯，\r\n因为现在的性能有点不够用啊」"
  },
  {
    "name": "帝雄",
    "message": "「如果你感兴趣的话可以过来看看……」"
  },
  {
    "name": "凪",
    "message": "「唔，一直问问题也不好，\r\n这次就算了」"
  },
  {
    "message": "社团活动休息啊……。突然空出了一大段时间。\r\n每天的课题在下课时间就做完了……。"
  },
  {
    "message": "对了。"
  },
  {
    "message": "我拿出手机，\r\n给灯理发了条消息。"
  },
  {
    "message": "凪「今天没打工的话，要不要去哪玩？」"
  },
  {
    "message": "回复很快，只写了一句「我想去！」。"
  },
  {
    "message": "放学后，我去教室接她。"
  },
  {
    "message": "刚约好，下课铃就响了。"
  },
  {
    "message": "多亏了放学后有期待的活动，\r\n下午的课我应该能集中精神撑过去。"
  }
]