[
  {
    "message": "与可靠的伙伴们讨论完，\r\n做好周全的准备后，我们前往珠贺良区。"
  },
  {
    "message": "有人紧张得表情僵硬，有人表现得跟平时一样\r\n虽然每个人各有不同，但心情是一样的。"
  },
  {
    "message": "解决完问题后，我们带着龙司回去了。"
  },
  {
    "message": "我们一边想着这些，\r\n一边往分隔墙的深处前进。"
  },
  {
    "message": "没有发生什么意外，\r\n我们顺利地进入了分隔墙3。"
  },
  {
    "message": "感觉不错，我这么想着，转向大家。"
  },
  {
    "name": "凪",
    "message": "「那么，接下来才是真正的开始。\r\n再过一会儿就要进入分隔墙4了」"
  },
  {
    "name": "凪",
    "message": "「说实话，分隔墙4以后\r\n我也只去过几次」"
  },
  {
    "name": "凪",
    "message": "「所以我也不知道会发生什么」"
  },
  {
    "name": "凪",
    "message": "「不管多小的事情都行，\r\n如果有什么发现的话请告诉我」"
  },
  {
    "name": "凪",
    "message": "「因为这里不是常识能通用的地方……」"
  },
  {
    "message": "灯理和东欧咽了咽口水\r\n我看得出来。"
  },
  {
    "name": "伊舞",
    "message": "「虽然只是感觉，\r\n但感觉前面的空气很混浊」"
  },
  {
    "name": "伊舞",
    "message": "「凪小姐说得没错，从这里开始\r\n要绷紧神经」"
  },
  {
    "name": "帝雄",
    "message": "「感觉有点冷……」"
  },
  {
    "name": "灯理",
    "message": "「我也是第一次有这种讨厌的感觉……」"
  },
  {
    "name": "伊舞",
    "message": "「我感觉，这附近有东西在盯着我们。\r\n如果你们觉得撑不住了，要立刻告诉我」"
  },
  {
    "name": "伊舞",
    "message": "「就算是我也没办法同时抱着三个人走，\r\n如果真的不行了，就先撤退吧」"
  },
  {
    "message": "听了伊舞的话，\r\n灯理捏了捏衣服的边角。"
  },
  {
    "name": "凪",
    "message": "「没事吧？」"
  },
  {
    "name": "灯理",
    "message": "「没事，我早就料到会这样了」"
  },
  {
    "name": "凪",
    "message": "「好，绝对不能离开伊舞身边哦」"
  },
  {
    "name": "伊舞",
    "message": "「你没有说「从我身边离开」这种话，\r\n真是凪的优点呢～」"
  },
  {
    "name": "凪",
    "message": "「别开玩笑了」"
  },
  {
    "name": "伊舞",
    "message": "「好～」"
  },
  {
    "message": "或许是伊舞的玩笑起了作用，\r\n灯理和帝雄的表情稍微变得开朗了一些。"
  },
  {
    "message": "虽然需要保持警戒，但过度的紧张会削减精神。"
  },
  {
    "message": "看准了两人放松下来的时候，\r\n我迈开步伐，这时玖玖瑠发来了通讯。"
  },
  {
    "name": "玖玖瑠",
    "message": "「凪，你有听到吗？」"
  },
  {
    "name": "凪",
    "message": "「嗯，没问题。没有任何问题」"
  },
  {
    "name": "玖玖瑠",
    "message": "「这边也已经掌握了你们的行踪。\r\n有什么事的话我会逐一通知你们的，放心吧」"
  },
  {
    "name": "凪",
    "message": "「我知道了。话说回来，\r\n居然能推算出我们详细的所在位置，真是厉害啊」"
  },
  {
    "name": "奏命",
    "message": "「我用了一色家的权利借用了卫星。\r\n只要有人能操作卫星的话，就不是不可能的事」"
  },
  {
    "name": "玖玖瑠",
    "message": "「就是这么回事」"
  },
  {
    "name": "凪",
    "message": "「虽然你讲得很轻松，\r\n但你是不是在做很不得了的事啊？」"
  },
  {
    "name": "奏命",
    "message": "「呵呵，\r\n要是失败的话可就不得了了」"
  },
  {
    "name": "凪",
    "message": "「感觉胃都要痛起来了」"
  },
  {
    "name": "奏命",
    "message": "「看来你还有开玩笑的余力，\r\n真是太好了。\r\n祝你好运」"
  },
  {
    "name": "玖玖瑠",
    "message": "「就交给我吧，我会完美地辅助你的」"
  },
  {
    "name": "凪",
    "message": "「啊啊，拜托你了」"
  },
  {
    "message": "凪「唔，嗯，唔嗯」"
  },
  {
    "message": "<reserved_106>根据以下术语表（可以为空，格式为src->dst #备注）："
  },
  {
    "message": "玖玖瑠的引导下，我们顺利地进入了四号街区\r\n顺利得让人有些吃惊。"
  },
  {
    "message": "远处传来怒吼和某种东西破裂的声音\r\n但也就这些了。"
  },
  {
    "message": "周围没有其他人影，感觉不到危险。"
  },
  {
    "message": "虽然只告诉我们最低限度的必要情报，\r\n但肯定是在回避可能会发生麻烦的地方。"
  },
  {
    "message": "我一边感谢着，\r\n一边一个劲地朝着目的地前进。"
  },
  {
    "message": "然后我们到达了目的地。"
  },
  {
    "message": "在珠贺良区被认为最危险的六号管理区。"
  },
  {
    "message": "那里是异常的空间。"
  },
  {
    "message": "虽然可以说完全看不到人的身影，\r\n但到处都能感觉到视线。"
  },
  {
    "message": "可怕的是，谁都不打算隐藏视线。"
  },
  {
    "message": "在监视着我们。\r\n如果发生什么，马上就能收拾掉。"
  },
  {
    "message": "这里的居民们是这样告诉我们的。"
  },
  {
    "message": "紧张感太强，我流出了冷汗。"
  },
  {
    "name": "凪",
    "message": "「伊舞……警察能进到这里来吗」"
  },
  {
    "name": "伊舞",
    "message": "「很遗憾，只能进到三号管理区。\r\n如果发生什么，必须自己逃到那里」"
  },
  {
    "name": "凪",
    "message": "「这样啊……」"
  },
  {
    "name": "帝雄",
    "message": "「我们穿制服来真的好吗……」"
  },
  {
    "name": "伊舞",
    "message": "「虽然有好有坏，\r\n但这次是作为身份证的替代品」"
  },
  {
    "name": "伊舞",
    "message": "「如果穿着同样的制服来找狮童同学，\r\n这里的居民也会马上知道吧？」"
  },
  {
    "name": "伊舞",
    "message": "「樱元学园的学生有利用价值，\r\n但同时也是危险物品」"
  },
  {
    "name": "伊舞",
    "message": "「如果随便对我们出手，\r\n反而很有可能被击溃」"
  },
  {
    "name": "伊舞",
    "message": "「所以不想和我们扯上关系的人，\r\n会自动避开我们……应该吧」"
  },
  {
    "name": "伊舞",
    "message": "「不过，如果有很多人会想些蠢事，\r\n那我们就有点麻烦了……」"
  },
  {
    "name": "灯理",
    "message": "「哥哥……你看，那里好像有人」"
  },
  {
    "name": "帝雄",
    "message": "「诶，难道是龙司……？」"
  },
  {
    "message": "我制止了想要确认真身的两人，\r\n一边警戒一边靠近。"
  },
  {
    "message": "倒在地上的是个瘦弱的女性。"
  },
  {
    "message": "眼神空洞，\r\n即使我们靠近了她也没有看过来。"
  },
  {
    "name": "伊舞",
    "message": "「……是药物吗。\r\n玖玖瑠，先把这个地方标记一下」"
  },
  {
    "name": "玖玖瑠",
    "message": "「那倒是没问题……」"
  },
  {
    "name": "伊舞",
    "message": "「我知道的。虽然很难介入，\r\n但我不想放着不管……」"
  },
  {
    "name": "灯理",
    "message": "「伊舞酱……」"
  },
  {
    "name": "伊舞",
    "message": "「没事的，我们先走吧。\r\n大家，不要离开我身边哦」"
  },
  {
    "message": "我们警戒着四周，朝着目的地前进。"
  },
  {
    "message": "与其他区域不同，\r\n这里本来就没什么安全的地方。"
  },
  {
    "message": "尽管有玖玖瑠为我们带路，\r\n但附近还是能听到危险的声音。"
  },
  {
    "message": "我听到声音后环视四周，\r\n发现有人倒在地上，还有血迹。"
  },
  {
    "message": "我祈祷着倒在地上的人中没有樱元学园的校服，\r\n在非日常的空间中继续前进……。"
  },
  {
    "message": "差不多快到老奶奶告诉我们的地方了……。"
  },
  {
    "name": "凪",
    "message": "「应该是在这附近……」"
  },
  {
    "message": "停下脚步，环视四周。"
  },
  {
    "message": "周围都是些破旧的建筑。\r\n龙司就在其中的某处吧。"
  },
  {
    "message": "在暗淡的窗户玻璃的另一侧，\r\n我看到了人影。"
  },
  {
    "name": "伊舞",
    "message": "「凪，刚才那是……」"
  },
  {
    "name": "凪",
    "message": "「伊舞也看到了吗」"
  },
  {
    "name": "灯理",
    "message": "「你们两个，找到他了吗？」"
  },
  {
    "name": "伊舞",
    "message": "「嗯。在废弃大楼里看到了人影，\r\n大概是狮童同学」"
  },
  {
    "name": "帝雄",
    "message": "「太好了……是哪栋大楼？」"
  },
  {
    "name": "凪",
    "message": "「就是那里……」"
  },
  {
    "message": "我躲在暗处，指着那栋大楼。\r\n附近有好几个看起来很凶恶的男人。"
  },
  {
    "name": "伊舞",
    "message": "「感觉像是坏人的据点呢」"
  },
  {
    "name": "灯理",
    "message": "「呜……该怎么办才好呢」"
  },
  {
    "name": "凪",
    "message": "「先确认一下情况吧。\r\n玖玖瑠，你能做到吗？」"
  },
  {
    "name": "玖玖瑠",
    "message": "「当然」"
  },
  {
    "name": "玖玖瑠",
    "message": "「总之，看守的配置大概就是这样」"
  },
  {
    "name": "伊舞",
    "message": "「谢谢。这样应该没问题了」"
  },
  {
    "name": "玖玖瑠",
    "message": "「不过，里面的人数还不清楚，要小心」"
  },
  {
    "name": "玖玖瑠",
    "message": "「为了以防万一，\r\n我先找出最合适的逃跑路线」"
  },
  {
    "name": "玖玖瑠",
    "message": "「如果发生了什么问题就马上告诉我」"
  },
  {
    "name": "凪",
    "message": "「知道了。谢谢」"
  },
  {
    "message": "都受到这么周到的照顾了，\r\n可不能失败啊。"
  },
  {
    "message": "我这样告诉自己，\r\n鼓起干劲努力判断状况。"
  },
  {
    "name": "凪",
    "message": "「……不愧是玖玖瑠啊」"
  },
  {
    "name": "凪",
    "message": "「一边说话一边把我引到\r\n监视死角的地方」"
  },
  {
    "name": "伊舞",
    "message": "「嗯，真的非常感谢。\r\n从这个位置的话，很容易设置陷阱」"
  },
  {
    "name": "伊舞",
    "message": "「但是，现在不管什么情况我都不觉得会输」"
  },
  {
    "name": "凪",
    "message": "「真可靠啊。但是，不要乱来啊」"
  },
  {
    "name": "伊舞",
    "message": "「这点我明白。\r\n现在我不是一个人了」"
  },
  {
    "name": "灯理",
    "message": "「那么……作战开始\r\n可以吗？」"
  },
  {
    "name": "凪",
    "message": "「那么，开始吧」"
  },
  {
    "name": "伊舞",
    "message": "「首先由我过去把监视者打倒，\r\n你们等一下」"
  },
  {
    "message": "我默默点头表示同意。"
  },
  {
    "message": "确认我的反应后，\r\n伊舞轻快地向前走去。"
  },
  {
    "message": "她从监视者的背后悄悄接近，\r\n但对方似乎没有注意到。"
  },
  {
    "message": "移动到射程范围内后，她慢慢摆出架势，\r\n对着对方的脖子使出回旋踢——！"
  },
  {
    "message": "然后伊舞立刻飞奔而出！"
  },
  {
    "message": "另一个监视者注意到情况不对，\r\n正要采取行动的时候，已经像断了线的木偶一样倒下了。"
  },
  {
    "name": "伊舞",
    "message": "「手感不错。我做得很好」"
  },
  {
    "message": "就这样，她把倒下的两人组\r\n像什么都没发生一样拖了过来。"
  },
  {
    "name": "凪",
    "message": "「看来你把一个不得了的逸才\r\n培养出来了啊」"
  },
  {
    "name": "凪",
    "message": "「你的身手真是了得。\r\n打倒第二个人的时候，我都不知道你做了什么」"
  },
  {
    "name": "伊舞",
    "message": "「啊，那是老师教我的……啊，\r\n这个说明就不用了吧」"
  },
  {
    "name": "伊舞",
    "message": "「好了，我们走吧」"
  },
  {
    "name": "凪",
    "message": "「在那之前我想确认一下这些家伙的随身物品」"
  },
  {
    "name": "灯理",
    "message": "「我看看……咦，这是什么？」"
  },
  {
    "name": "帝雄",
    "message": "「我猜是电击棒……。\r\n要带走吗？」"
  },
  {
    "name": "伊舞",
    "message": "「嗯，没收了比较省事」"
  },
  {
    "name": "伊舞",
    "message": "「除了我以外……果然还是凪吧」"
  },
  {
    "name": "伊舞",
    "message": "「如果发生意外情况，\r\n就用这个帮助灯理和成宫同学吧」"
  },
  {
    "name": "凪",
    "message": "「我祈祷着，不要发生需要使用这个的状况」"
  },
  {
    "name": "伊舞",
    "message": "「那么，既然入口已经确保了\r\n就赶紧进入大楼吧」"
  },
  {
    "name": "伊舞",
    "message": "「不用着急，\r\n注意不要发出声音哦」"
  },
  {
    "message": "我们走进了\r\n到处都有裂缝的废弃大楼。"
  },
  {
    "message": "因为不知道什么时候\r\n入口的看守会发现我们。"
  },
  {
    "message": "我意识到接下来要和时间赛跑，\r\n屏住呼吸开始行动。"
  },
  {
    "message": "恐怕，前进的方向\r\n会有更大的危险在等待着我们。"
  },
  {
    "message": "如果发生什么情况，就由我来……。"
  },
  {
    "message": "我下定决心，握紧电击棒。"
  }
]