[
  {
    "message": "いつも通りに目を覚まして、ファイブと学習塔に向かう。"
  },
  {
    "message": "馴染んできた通学路では、変わらぬ遭遇が待ち受けていた。"
  },
  {
    "name": "くくる",
    "message": "「ん……凪。おはよう。ばいばい」"
  },
  {
    "name": "凪",
    "message": "「挨拶とお別れを一緒にするなっての」"
  },
  {
    "name": "くくる",
    "message": "「考え事をしてる。朝の貴重な時間だから邪魔しないで。\r\nばいばい」"
  },
  {
    "name": "凪",
    "message": "「マイペースなヤツだなあ」"
  },
  {
    "name": "凪",
    "message": "「まあ、挨拶してくれただけでも前進してる証拠か」"
  },
  {
    "name": "イヴ",
    "message": "「あらおはよう、凪さん」"
  },
  {
    "name": "凪",
    "message": "「イヴ、待ち伏せか？」"
  },
  {
    "name": "イヴ",
    "message": "「あのねえ、私は忍者じゃないの。\r\nいっつも狙って登場してる訳じゃないんだから」"
  },
  {
    "name": "イヴ",
    "message": "「今日は朝早くに、学生会室に行っておきたいの」"
  },
  {
    "name": "イヴ",
    "message": "「私とくくるが卒業承認をあげた件を、\r\n会長に報告するよ」"
  },
  {
    "name": "イヴ",
    "message": "「早ければお昼に、遅くても放課後には呼び出されると\r\n思うから、心の準備はしっかりね」"
  },
  {
    "name": "凪",
    "message": "「ああ。サンキュー」"
  },
  {
    "message": "自席に腰を下ろして、カバンの中から参考書を取り出す。"
  },
  {
    "name": "凪",
    "message": "（少しでも自主勉を進めておかないとな……）"
  },
  {
    "message": "授業についていけないという課題をクリアするためにも、\r\n図書館から借りた参考書を読み進めた。"
  },
  {
    "message": "合間に出てくる問題を解きつつ、\r\nふと、教室内に視線をやる。"
  },
  {
    "message": "まだ人影はまばらだが、徐々に埋まってくるだろう。\r\nしかし……。"
  },
  {
    "name": "凪",
    "message": "（龍司は、今日も休みかな）"
  },
  {
    "message": "アイツの取り巻きは姿を見かけるのだが、\r\n龍司本人は欠席が続いている。"
  },
  {
    "message": "逆恨みによる逆襲を警戒していたが、\r\n今のところ動きはない。取り巻きも大人しくしていた。"
  },
  {
    "name": "凪",
    "message": "（俺じゃなく、別の人間を狙うとしたら、\r\nテイオー、もしくはトウリか？）"
  },
  {
    "name": "凪",
    "message": "（いや、トウリも表向きは泉家のご令嬢。\r\n出自がバレない限りは狙われることはない）"
  },
  {
    "message": "珠賀良区の人間が桜元学園に入り込むのは、\r\n相当あり得ないことなのだ。"
  },
  {
    "message": "親しそうに話している姿を見られた所で、\r\nまさか家族だと、攻め所だとは思わないだろう。"
  },
  {
    "name": "凪",
    "message": "（有事に備えて、\r\n自分自身の守りをもっと固めるべきか……）"
  },
  {
    "name": "凪",
    "message": "（……いや、気を張ってばかりではいられない。\r\nイヴの言葉じゃないが、心構えだけしておくか）"
  },
  {
    "message": "放課後――イヴの予想通りに事が動いた。"
  },
  {
    "name": "凪",
    "message": "「三人だけなのか？\r\nてっきり全員が集まっているかと思ってたのに」"
  },
  {
    "name": "空",
    "message": "「何か不都合でも？」"
  },
  {
    "name": "花",
    "message": "「他の方もいないと話がしづらいようなら、\r\n今からでも呼びますけど」"
  },
  {
    "name": "凪",
    "message": "「いや大丈夫だ。それで、用件は？」"
  },
  {
    "message": "両隣を双子に守られるようにして座っていた\r\n学生会長へと視線を向ける。"
  },
  {
    "name": "奏命",
    "message": "「指導を任せたのは、文化部総括のくくるだった」"
  },
  {
    "name": "奏命",
    "message": "「なのに、指導開始から二日足らずで、\r\n運動部総括の卒業承認まで得てくるだなんて……」"
  },
  {
    "name": "奏命",
    "message": "「非常識極まりない。あなたって、面白い人ね」"
  },
  {
    "name": "凪",
    "message": "「褒められてるんだよな？」"
  },
  {
    "name": "奏命",
    "message": "「もちろん。どんな手を使ったにせよ、\r\n結果を得られたのはあなたの才能よ」"
  },
  {
    "name": "凪",
    "message": "（現実は、条件付きでの承認なんだけどな……）"
  },
  {
    "message": "会長の下着の色を確認出来なかったら\r\n即取り下げというふざけた条件がついている。"
  },
  {
    "message": "悠長にやっていたら文句も言われるだろうし、\r\nまったく難儀なものである。"
  },
  {
    "name": "花",
    "message": "「ちなみに、何をしたんです？」"
  },
  {
    "name": "花",
    "message": "「イヴちゃんやくくるちゃんを、\r\n非人道的な手段で脅したりしてないです？」"
  },
  {
    "name": "凪",
    "message": "「そんなことする訳ないだろ。\r\n純粋に認めてくれたんだよ」"
  },
  {
    "name": "空",
    "message": "「本当に？　嘘をついてもすぐにバレるからね」"
  },
  {
    "name": "凪",
    "message": "「もっと信じてもいいんじゃないか？　二人をさ」"
  },
  {
    "name": "凪",
    "message": "「運動部総括も、文化部総括も、\r\n一方ならぬ才女だろうに」"
  },
  {
    "name": "花",
    "message": "「うっ……」"
  },
  {
    "name": "空",
    "message": "「それは……そうだけど」"
  },
  {
    "name": "奏命",
    "message": "「花、空。あなた達の負けよ」"
  },
  {
    "name": "奏命",
    "message": "「……いいでしょう、布波能凪。\r\n認めるわ、あなたは常人ではないと」"
  },
  {
    "name": "奏命",
    "message": "「獅童龍司、夜刀くくる、蓼科イヴ……」"
  },
  {
    "name": "奏命",
    "message": "「桜元学園の最高位に立つ学生会のメンバーを、\r\nことごとく踏み倒す、あるいは懐柔するその力」"
  },
  {
    "name": "奏命",
    "message": "「正確に判断してあげる。私自身の目で」"
  },
  {
    "name": "凪",
    "message": "「ついに学生会長のお出ましって訳だ」"
  },
  {
    "name": "凪",
    "message": "「くくるとイヴ、そして会長の卒業承認を貰えたら、\r\nいつ何時でも卒業出来るんだよな」"
  },
  {
    "name": "奏命",
    "message": "「最終的には学園長の承認印が必要だけれど、\r\nそれは儀礼的なものだと思って貰って構わない」"
  },
  {
    "name": "奏命",
    "message": "「明日か、一週間後か、あるいは一か月後か……。\r\nいつ何時であろうと構わないわ」"
  },
  {
    "name": "奏命",
    "message": "「私達三人が、自らの責任の下であなたを認めたら、\r\n晴れて桜元学園の卒業生という名誉を手に出来る」"
  },
  {
    "name": "凪",
    "message": "「学生会のメンバーと結婚するっていうゴールは\r\nまだ遠そうだが、卒業までのゴールは見えてきた」"
  },
  {
    "name": "凪",
    "message": "「獲らせて貰うぞ、会長の承認も」"
  },
  {
    "name": "奏命",
    "message": "「ふふふ……短期間でここまで辿り着くなんて、\r\nこれまでの記録を[txruby text=\"さかのぼ\"]遡[txruby]ってもあなたが初めて」"
  },
  {
    "name": "奏命",
    "message": "「誇るといいわ。そして存分に、私に力を示して頂戴」"
  },
  {
    "name": "奏命",
    "message": "「では、最初の課題を伝える」"
  },
  {
    "name": "凪",
    "message": "「最初の課題……？」"
  },
  {
    "name": "奏命",
    "message": "「あら、一度の指導であなたのすべてを\r\n推し量れるような、無理難題を押しつけられたいの？」"
  },
  {
    "name": "凪",
    "message": "「遠慮します！　イージーな指導内容でよろしくです！」"
  },
  {
    "name": "奏命",
    "message": "「コーヒーを用意しなさい」"
  },
  {
    "name": "凪",
    "message": "「……ん？」"
  },
  {
    "name": "凪",
    "message": "「コーヒーって、何かの隠語か？」"
  },
  {
    "name": "奏命",
    "message": "「あなたの世界には、コーヒーって隠語があるの？」"
  },
  {
    "name": "凪",
    "message": "「いやないけど。ないと、思う」"
  },
  {
    "name": "奏命",
    "message": "「そうなの。興味を持って損をしたわ」"
  },
  {
    "name": "奏命",
    "message": "「単純に、コーヒーを持ってくればいいの」"
  },
  {
    "name": "凪",
    "message": "「それだけ？」"
  },
  {
    "name": "奏命",
    "message": "「小手調べには、これくらいが丁度いいのよ」"
  },
  {
    "name": "凪",
    "message": "「ふ、む……」"
  },
  {
    "name": "凪",
    "message": "「なあ、部屋の隅にあるアレ、\r\nもしかしてコーヒーマシンか？」"
  },
  {
    "message": "この部屋に入る度、感じていた香り。"
  },
  {
    "message": "空間そのものに染みついているコーヒーの香りは、\r\nあそこから発せられていたに違いない。"
  },
  {
    "name": "花",
    "message": "「コンビニ各社がしのぎを削りながら開発している\r\nコーヒーマシンを元にして作って貰った、特注品です」"
  },
  {
    "name": "花",
    "message": "「企業努力の結晶とも言える代物ですよー」"
  },
  {
    "name": "花",
    "message": "「奏命様の肥えた舌を満足させるには\r\nアレくらいのを用意しないと無理なので……」"
  },
  {
    "name": "空",
    "message": "「美味しいコーヒーを楽に淹れられるっていうのも\r\n考え物だけどね。奏命様はすぐに飲み過ぎちゃうから」"
  },
  {
    "name": "花",
    "message": "「空ちゃん、アル中みたいに言っちゃダメです」"
  },
  {
    "name": "奏命",
    "message": "「…………」"
  },
  {
    "name": "凪",
    "message": "「ちなみに、あのコーヒーマシン、使っていい？」"
  },
  {
    "name": "奏命",
    "message": "「手近の物で課題をクリアする気？\r\nいい訳ないでしょう。それなら花か空に用意して貰うわ」"
  },
  {
    "name": "凪",
    "message": "「ですよねー」"
  },
  {
    "name": "奏命",
    "message": "「ちなみに、ちゃんと意図のある課題だから。\r\n無駄な雑用を与えられたとは思わない方が身のためよ」"
  },
  {
    "name": "凪",
    "message": "「からかわれてる訳じゃないんだな……」"
  },
  {
    "name": "凪",
    "message": "「…………」"
  },
  {
    "name": "奏命",
    "message": "「ん？　まだ気になることでも？」"
  },
  {
    "message": "会長の両隣は、双子によりガッチリと守られている。"
  },
  {
    "name": "凪",
    "message": "（下着を盗むのは、今は無理そうだな……）"
  },
  {
    "message": "下手を打って、警戒されたくもない。"
  },
  {
    "name": "凪",
    "message": "「何でもない。ちょっと考えてみるよ」"
  },
  {
    "message": "課題について承諾の意を短く伝えてから、\r\n大人しく部屋を退出した。"
  },
  {
    "name": "花",
    "message": "「待つのです」"
  },
  {
    "message": "廊下に出るとすぐ、\r\n双子が追いかけるようにやってきた。"
  },
  {
    "name": "空",
    "message": "「突然みんなにプロポーズする非常識な人が、\r\n奏命様に認められたのは意外だけど……」"
  },
  {
    "name": "空",
    "message": "「期待を裏切らないように頑張ってね。\r\nはいこれ、コーヒーを用意するための軍資金」"
  },
  {
    "name": "凪",
    "message": "「手厚い支援だな、ありがとう」"
  },
  {
    "name": "空",
    "message": "「あなたのためじゃないから。奏命様のためだから」"
  },
  {
    "name": "花",
    "message": "「花と空ちゃんの電話番号も教えておきますから、\r\n用意が出来たら、すぐに連絡をください」"
  },
  {
    "name": "花",
    "message": "「片方にかけて繋がらなかったら、\r\nもう片方へお願いします。どっちかは繋がるはずです」"
  },
  {
    "name": "凪",
    "message": "「分かった、都合の悪い時間とかってあるか？」"
  },
  {
    "name": "花",
    "message": "「よっぽど非常識な時間帯でなければ、大丈夫です。\r\nすぐ奏命様に取り次ぎますよ」"
  },
  {
    "name": "空",
    "message": "「奏命様が認めて直々に指導すると決めた相手を\r\n無碍に扱ったりはしないので、ご心配なく」"
  },
  {
    "name": "花",
    "message": "「不本意と言えば超不本意ですけどねー」"
  },
  {
    "name": "凪",
    "message": "「ひでえ」"
  },
  {
    "name": "花",
    "message": "「奏命様の時間を無駄にさせないよう、\r\n頑張ってこいです！　いいですね」"
  },
  {
    "name": "空",
    "message": "「話は以上。行こう、花ちゃん」"
  },
  {
    "name": "凪",
    "message": "「やれやれ……コーヒーかあ」"
  },
  {
    "name": "凪",
    "message": "「……ん？」"
  },
  {
    "message": "廊下を歩いていると、自販機がふと目に付いた。"
  },
  {
    "name": "凪",
    "message": "「…………」"
  },
  {
    "message": "この課題には、ちゃんとした意図があると言っていた。"
  },
  {
    "name": "凪",
    "message": "（ヒントを得るためにも、やるだけやってみるか）"
  },
  {
    "name": "凪",
    "message": "「ホットかアイスか……うーん」"
  },
  {
    "message": "好み、あるいは気分を聞いておくべきだったなあ。"
  },
  {
    "name": "凪",
    "message": "「お。新発売か……」"
  },
  {
    "message": "タッチパネルを押せば、ガチャンッという自販機特有の\r\n音がして、下の受け取り口に現物が出てくる。"
  },
  {
    "message": "温かい缶コーヒーを手に持ちながら、\r\nさっそく教えて貰ったばかりの電話番号をタップした。"
  },
  {
    "name": "空",
    "message": "「もしもし。布波能くん？　どうしたの？」"
  },
  {
    "message": "三コール以内に出てくれた相手に、穏やかな声を返す。"
  },
  {
    "name": "凪",
    "message": "「コーヒー用意出来た。持ってっていい？」"
  },
  {
    "name": "空",
    "message": "「はやっ！？　え、うん、分かった。\r\nじゃあ学生会室に来て」"
  },
  {
    "name": "奏命",
    "message": "「想像を超えた速さを、褒めるべきか、貶すべきか」"
  },
  {
    "name": "凪",
    "message": "「まずは当たりをつける！　これでもくらえ！」"
  },
  {
    "message": "バーンッ！！　と何でもない缶コーヒーを出した。"
  },
  {
    "name": "凪",
    "message": "「新発売だ！」"
  },
  {
    "name": "奏命",
    "message": "「知ってるわよ」"
  },
  {
    "name": "凪",
    "message": "「あ、マジ？」"
  },
  {
    "name": "奏命",
    "message": "「新発売の缶コーヒーはすべてチェックしてるわ」"
  },
  {
    "name": "凪",
    "message": "「……会長ってコーヒーマニアだったりする？」"
  },
  {
    "name": "奏命",
    "message": "「それ程でもないわ」"
  },
  {
    "name": "花",
    "message": "「それ程でもありますからね」"
  },
  {
    "name": "空",
    "message": "「プロも顔負けだから気をつけてね」"
  },
  {
    "name": "凪",
    "message": "「相当なヤツじゃねえか……」"
  },
  {
    "name": "凪",
    "message": "（コーヒーを持ってくるだけとか言いながら、\r\nこれめっちゃ難しい課題じゃないか……？）"
  },
  {
    "message": "嫌な予感がしつつも、会長の反応を伺う。"
  },
  {
    "name": "奏命",
    "message": "「何を考えて、これを買ってきたの？」"
  },
  {
    "name": "凪",
    "message": "「課題に対して、今はヒント０だからな。\r\n当たりをつけようかと思って」"
  },
  {
    "name": "凪",
    "message": "「これで課題をクリア出来るとは思ってない」"
  },
  {
    "name": "奏命",
    "message": "「それならば、できる限り早く用意して持ってきたのは\r\n悪手ではないわね」"
  },
  {
    "name": "奏命",
    "message": "「次に期待しているわ」"
  },
  {
    "name": "凪",
    "message": "「……それだけ？」"
  },
  {
    "name": "奏命",
    "message": "「やり直しで」"
  },
  {
    "name": "凪",
    "message": "「そうするつもりだけど、もうちょいヒントくれ。\r\nせめて好みや気分を教えてくれ。アイスかホットか」"
  },
  {
    "name": "奏命",
    "message": "「任せるわ」"
  },
  {
    "name": "凪",
    "message": "「ほほーーーん……。\r\n昔、妹に言われた台詞があってだな」"
  },
  {
    "name": "凪",
    "message": "「何が食べたいかって聞いた時、\r\nなんでもいいって返されるのが一番困るんだと」"
  },
  {
    "name": "凪",
    "message": "「そういう事態を避けたいだけなんだが？」"
  },
  {
    "name": "奏命",
    "message": "「いいわね、そういう気持ちがあれば大丈夫よ。\r\n頑張りなさい」"
  },
  {
    "name": "奏命",
    "message": "「あ、この缶コーヒーは貰っておくわ」"
  },
  {
    "message": "慣れた手つきで、\r\n片手で缶コーヒーのタブを弄って開ける。"
  },
  {
    "message": "飲み慣れた仕草に、俺は苦笑いを浮かべてしまった。"
  }
]