[
  {
    "name": "凪",
    "message": "「もう無理……死んだ……脳が死んだ……」"
  },
  {
    "message": "文字通り、日が暮れるまでたたき込まれた……。"
  },
  {
    "message": "疲労困憊している俺を見て、\r\n奏命がぱたりと問題集を閉じる。"
  },
  {
    "name": "凪",
    "message": "「終わったか……やっとだ……ああ、俺には見える。\r\n天使の姿が見えるうぅぅぅ……！！」"
  },
  {
    "message": "とてつもなくハードな長距離走を終えた後みたいな\r\n感覚でいると、空と花が部屋に入ってきた。"
  },
  {
    "name": "花",
    "message": "「失礼します、そろそろ夕食の時間ですし、\r\n切り上げてはと思いましてー」"
  },
  {
    "name": "空",
    "message": "「こちらの仕事はしっかりと\r\n終わらせておきましたので、ご安心ください」"
  },
  {
    "name": "奏命",
    "message": "「ありがとう。\r\n後で軽く報告をしてちょうだい」"
  },
  {
    "name": "花",
    "message": "「はい。……ちなみに今日は\r\nエッチなこととかしていませんよね？」"
  },
  {
    "name": "奏命",
    "message": "「疑われるなんて心外だわ。勉強をそっちのけで\r\nセックスにいそしんでいたとでも？」"
  },
  {
    "name": "花",
    "message": "「ここ最近の奏命様の積極性を考えたら、\r\n有り得てしまうのかなぁと思ってしまって」"
  },
  {
    "name": "奏命",
    "message": "「ふふっ、花の許しが出るなら\r\nそうすれば良かったかもしれないわね」"
  },
  {
    "name": "空",
    "message": "「花ちゃんが許しても空が許していませんよ、\r\n奏命様！」"
  },
  {
    "name": "花",
    "message": "「は、花だって許してないんですからねっ！」"
  },
  {
    "name": "空",
    "message": "「ダメですよ！　少なくとも結婚するまでの性交は\r\n恋愛感情抜きじゃしちゃだめです」"
  },
  {
    "name": "奏命",
    "message": "「はいはい、もうわかっているわ。冗談よ」"
  },
  {
    "name": "花",
    "message": "「奏命様のは冗談に聞こえないんです」"
  },
  {
    "name": "空",
    "message": "「ひとまずは布波能くんにしっかり\r\nお願いしておくしかなさそうだね」"
  },
  {
    "message": "双子がジッ……とこっちを見てくる。"
  },
  {
    "message": "いくら奏命が肉体関係を持ちたがっていても\r\n一人では成立しない。"
  },
  {
    "message": "つまり……分かってるよね？"
  },
  {
    "message": "言葉にはしていないが、そういう意図が\r\n込められているとはっきり伝わってきた。"
  },
  {
    "name": "凪",
    "message": "「ワカッテマス」"
  },
  {
    "name": "空",
    "message": "「信じてるからね」"
  },
  {
    "name": "花",
    "message": "「布波能くんが最後の砦なんですから、\r\n誘惑に負けちゃだめですよっ！」"
  },
  {
    "name": "奏命",
    "message": "「さてと、バカやってないで行くわよ。\r\n空腹でお腹が悲鳴を上げそうだわ」"
  },
  {
    "message": "夕食を終えると、ふいに奏命が口を開いた。"
  },
  {
    "name": "奏命",
    "message": "「仕事の都合で不定期にはなるけれど、\r\n可能な限りは私が勉強の面倒を見ることにするわ」"
  },
  {
    "name": "奏命",
    "message": "「呼ばれたら学生会室に顔を出すように」"
  },
  {
    "name": "凪",
    "message": "「ワァ……ウレシイナァ……」"
  },
  {
    "name": "奏命",
    "message": "「見え透いた嘘を言うくらいなら\r\nはっきりと本音を口になさい」"
  },
  {
    "name": "凪",
    "message": "「奏命と過ごせるのは嬉しいけど、\r\nやり方がな」"
  },
  {
    "name": "凪",
    "message": "「こちとら脳が焼き切れてしまいそうだったので……」"
  },
  {
    "name": "凪",
    "message": "「次からはもう少し優しくしてくれると\r\n嬉しいかなーなんて」"
  },
  {
    "name": "奏命",
    "message": "「あなたの経験値が上がればすぐに優しく感じるわ」"
  },
  {
    "name": "凪",
    "message": "「なる……ほど……？」"
  },
  {
    "name": "奏命",
    "message": "「私が教えているんだもの。\r\n少なくとも授業はすぐに易しく感じるはずよ」"
  },
  {
    "name": "凪",
    "message": "「それはありがたいが……」"
  },
  {
    "name": "凪",
    "message": "「そういやずっと疑問だったんだが、\r\n奏命って授業には出てるのか？」"
  },
  {
    "name": "奏命",
    "message": "「当然でしょう。学生会長とはいえ、\r\n桜元学園の一学生であることに変わりはないのだから」"
  },
  {
    "name": "凪",
    "message": "「はー……、それで仕事もしてるのか。すごいな」"
  },
  {
    "name": "凪",
    "message": "「でも、ぶっちゃけ奏命くらいできるなら\r\n授業にでる必要ってないだろ」"
  },
  {
    "name": "凪",
    "message": "「ルールに則って授業に参加するのは\r\n煩わしくないのか？」"
  },
  {
    "name": "奏命",
    "message": "「買いかぶりすぎよ、私にだって知らない知識はある。\r\n専門分野に特化した先生方の講義には満足している」"
  },
  {
    "name": "奏命",
    "message": "「腐っても桜元学園、出る意味のない授業があるとは\r\n口が裂けても言えないわ」"
  },
  {
    "name": "花",
    "message": "「あー、でも……つまらない授業の時の奏命様って、\r\nずーっと瞼を閉じて瞑想しているんですよね」"
  },
  {
    "name": "花",
    "message": "「寝てるのかなー、眠いのかなーって見てると、\r\nすぐに目を開けるんです。眠くないといわんばかりに」"
  },
  {
    "name": "奏命",
    "message": "「実際に眠くはないもの。体力を温存して、\r\n面白い内容の時に頭を働かせようとしているだけ」"
  },
  {
    "name": "花",
    "message": "「いーえ、ああいうときの奏命様はおねむなんです。\r\nだって毎回コーヒーが欲しそうな顔をしてますもん」"
  },
  {
    "name": "空",
    "message": "「ちょっと花ちゃん言い過ぎだよ、事実だとしても、\r\nもうちょっと言葉を丸くしないと」"
  },
  {
    "name": "奏命",
    "message": "「…………」"
  },
  {
    "name": "奏命",
    "message": "「そういえば凪、あなたからプロポーズをされた\r\n覚えがないわね」"
  },
  {
    "name": "凪",
    "message": "「あからさまに話題変えたな」"
  },
  {
    "name": "奏命",
    "message": "「なんのことかしら」"
  },
  {
    "name": "空",
    "message": "「こうなったらもう絶対認めないから\r\n諦めたほうがいいよ」"
  },
  {
    "name": "花",
    "message": "「ですね～」"
  },
  {
    "message": "そう言いながら、空と花は食器を片付けていく。"
  },
  {
    "message": "奏命の扱いに慣れてるなぁ。"
  },
  {
    "name": "奏命",
    "message": "「聞いてるの？　凪」"
  },
  {
    "name": "凪",
    "message": "「はいはい。えーと、プロポーズだっけ？」"
  },
  {
    "name": "奏命",
    "message": "「そうよ。私を恋に落とすのであれば、\r\nプロポーズって大切だと思わない？」"
  },
  {
    "name": "凪",
    "message": "「まあ……そういえばそうだな」"
  },
  {
    "name": "奏命",
    "message": "「煮え切らない返事ね」"
  },
  {
    "name": "凪",
    "message": "「……してほしいのか？」"
  },
  {
    "name": "奏命",
    "message": "「絶対に言ってほしいという訳ではないけれど、\r\nあなたがどんな言葉を選ぶのか、興味があるわ」"
  },
  {
    "name": "凪",
    "message": "「じゃあ……仕方ないな。少し恥ずかしいけど\r\nやってみるか」"
  },
  {
    "message": "奏命がチラリと目配せをすれば、空と花は何も言わずに\r\n一礼して下がる。"
  },
  {
    "message": "こういう所は、この主従関係は凄いなーと思う。\r\n以心伝心といいますか。"
  },
  {
    "name": "凪",
    "message": "「コホン……」"
  },
  {
    "name": "凪",
    "message": "「奏命。結婚しよう！」"
  },
  {
    "name": "奏命",
    "message": "「軽いわ、空気のように軽すぎる。やり直し」"
  },
  {
    "name": "凪",
    "message": "「気持ちは込めたよ！？」"
  },
  {
    "name": "奏命",
    "message": "「以前くくるにもしたそうじゃない。\r\nその時の方が気持ち、こもっていたんじゃなくて？」"
  },
  {
    "name": "凪",
    "message": "「あれは交渉する上での、カードの一つとして\r\n言っただけでなあ」"
  },
  {
    "name": "奏命",
    "message": "「私があなたに恋をするために必要だと考えれば\r\nできるはず。ほら頑張って」"
  },
  {
    "name": "凪",
    "message": "「最近、その言葉を使えば俺がなんでも言うことを\r\n聞くと思ってないか？　……いいんだけどさ」"
  },
  {
    "name": "奏命",
    "message": "「では、片膝をついて、私の指を優しく包み込むように\r\n触って、雰囲気を纏わせながらプロポーズしてみて」"
  },
  {
    "name": "凪",
    "message": "「注文が多すぎる！　そんな台詞、真顔で言って\r\n様になるのは奏命くらいだぞ」"
  },
  {
    "name": "奏命",
    "message": "「褒め言葉として受け取っておくわ。\r\nさあ、早くやりなさい」"
  },
  {
    "name": "凪",
    "message": "「ええいくそ！　分かった！」"
  },
  {
    "message": "注文通りに片膝をつき、奏命の指先を\r\n掲げた左手で受け止め、視線を向ける。"
  },
  {
    "message": "どこぞの騎士が姫を見上げる。\r\nそんなイメージを基にして、表情も作り直し口を開いた。"
  },
  {
    "name": "凪",
    "message": "「――結婚しよう、奏命」"
  },
  {
    "name": "奏命",
    "message": "「大して変わらないわね」"
  },
  {
    "name": "凪",
    "message": "「やり損かよチクショー！」"
  },
  {
    "name": "凪",
    "message": "「やっぱり今は無理だ」"
  },
  {
    "name": "凪",
    "message": "「俺がちゃんと奏命を好きになった後で、\r\nもう一回チャレンジさせてくれ」"
  },
  {
    "name": "奏命",
    "message": "「いいでしょう。その時を心待ちにしているわ」"
  },
  {
    "name": "奏命",
    "message": "「満足のいくプロポーズを受けられなかったし、\r\n凪には代わりのモノを差し出してもらいましょうか」"
  },
  {
    "name": "凪",
    "message": "「……んんん！？」"
  },
  {
    "name": "凪",
    "message": "「ちょっと待て、なんで近づいてくるんだ」"
  },
  {
    "name": "奏命",
    "message": "「わかっていることを口にするのは野暮だわ。\r\n私は言葉よりも深い契りを求めている」"
  },
  {
    "name": "奏命",
    "message": "「あなたも昨夜のことが忘れられないんでしょう？\r\n続きをしたいとも思っているはず」"
  },
  {
    "name": "凪",
    "message": "「思わない、と言ったら嘘になるけど……。\r\nそれとこれとは話が別だ！」"
  },
  {
    "name": "奏命",
    "message": "「ふふふっ、そんなに早口になって。\r\n焦っているのね」"
  },
  {
    "name": "凪",
    "message": "「逆に奏命が落ち着きすぎなんだって！」"
  },
  {
    "name": "凪",
    "message": "「契りっていうか……約束事をするのに、\r\n身体を使うなんてあり得ないだろ」"
  },
  {
    "name": "凪",
    "message": "「もっと自分を大切にしろ。いいな」"
  },
  {
    "name": "奏命",
    "message": "「…………」"
  },
  {
    "name": "奏命",
    "message": "「あなたって、バカね」"
  },
  {
    "name": "凪",
    "message": "「なんだとこのやろー」"
  },
  {
    "name": "奏命",
    "message": "「珠賀良区にいる頃に、\r\nエロ本を作っていたんでしょう？」"
  },
  {
    "name": "奏命",
    "message": "「性欲が強いくせに、どうして我慢できるの？」"
  },
  {
    "name": "凪",
    "message": "「性欲が強かろうと理性くらいあるわ。\r\n腹を空かせた狼になる気はないぞ」"
  },
  {
    "name": "奏命",
    "message": "「ええ、だから自分を大事にしろなんて言って\r\n私の心配が出来る」"
  },
  {
    "name": "奏命",
    "message": "「焦っていた理由が私のためだったのは\r\n悪くないわ」"
  },
  {
    "name": "凪",
    "message": "「そうかい、伝わってよかったよ」"
  },
  {
    "name": "奏命",
    "message": "「でも致命的な思い違いをしているわね、凪」"
  },
  {
    "name": "奏命",
    "message": "「私は自分を安売りはしていないの。抱いてもいいと\r\n思える相手にしか、こんな申し出はしない」"
  },
  {
    "name": "奏命",
    "message": "「分かったなら、口を閉じなさい。\r\nこれ以上、言葉を並べても意味がないわ」"
  },
  {
    "name": "凪",
    "message": "「……………………あ……あのなあ」"
  },
  {
    "name": "凪",
    "message": "「俺が、抱かれるのかよ」"
  },
  {
    "name": "奏命",
    "message": "「ええそうよ、私が抱かれるのではない。\r\n抱いてあげる」"
  },
  {
    "name": "凪",
    "message": "「俺、奥さん側かよ」"
  },
  {
    "name": "奏命",
    "message": "「古風な考え方ね。女が抱かれ、守られ続ける時代は\r\nとうの昔に終わったの」"
  },
  {
    "name": "奏命",
    "message": "「一色家の当主が、女である私になっているのが、\r\nその証明だとは思わない？」"
  },
  {
    "name": "凪",
    "message": "「…………」"
  },
  {
    "name": "奏命",
    "message": "「……最後の問いかけにしましょうか」"
  },
  {
    "name": "奏命",
    "message": "「私は一色家にあなたの血を入れるために婚約した。\r\nもしもそれを拒否し続けるのであれば……」"
  },
  {
    "name": "奏命",
    "message": "「無理強いはしないわ。選びなさい」"
  },
  {
    "message": "究極の選択過ぎやしないだろうか。"
  },
  {
    "message": "ここまで言わせて、それでも断るなら\r\n婚約を破棄するとでも言いたいのか。"
  },
  {
    "message": "違うような気もする。断っても、じゃあまた別の\r\n機会にとさらっと言われそうな気もする。"
  },
  {
    "message": "というか難しく考えずとも、いいんじゃないか。"
  },
  {
    "message": "こんなに美人で、世間には存在しない高嶺の花が、\r\n迫ってきているという貴重な機会。"
  },
  {
    "message": "受け入れた方が、得じゃないか。一人の男として。"
  },
  {
    "message": "ああなんか、もう一つ浮かんできた。"
  },
  {
    "message": "ここまで奏命に言わせておいて、断ったら、無礼だと\r\n微笑みながら説教されそうな気がする。"
  },
  {
    "name": "凪",
    "message": "「そう、だな……わかっ――」"
  },
  {
    "message": "――奏命に同意しようとした、その瞬間。"
  },
  {
    "message": "突如として、鋭い寒気が背筋を貫いた。"
  },
  {
    "name": "空・花",
    "message": "「――――――――――」"
  },
  {
    "message": "振り向いて確かめたいけど確かめちゃいけない感覚。"
  },
  {
    "message": "なんか後ろ向いたら死にそうな気がする！"
  },
  {
    "name": "凪",
    "message": "「やっぱり断る！！　セックスはなしだ！！」"
  },
  {
    "name": "奏命",
    "message": "「ほほう？　それなら――」"
  },
  {
    "name": "凪",
    "message": "「同時に！　婚約破棄も断りまーす！！\r\n世の中には諦めちゃいけないことがあると思いまぁす！」"
  },
  {
    "name": "花",
    "message": "「よーくぞ言いましたぁぁぁあ、布波能くんっ！」"
  },
  {
    "name": "空",
    "message": "「えらいっっ！！！　偉すぎるよっ！」"
  },
  {
    "message": "さっきまでズシリと重くのしかかっていたプレッシャー。"
  },
  {
    "message": "それが嘘みたいに立ち消えて、爽快な気分になった。"
  },
  {
    "name": "凪",
    "message": "「ハッハッハッハッハ！！」"
  },
  {
    "message": "よし！　よくやった俺！\r\nさすがは珠賀良区で生き延びてきただけはアルネッ！！"
  },
  {
    "name": "奏命",
    "message": "「やっぱり見ていたのね。\r\n最近は干渉がすぎるんじゃない？」"
  },
  {
    "name": "空",
    "message": "「それくらい奏命様が心配なんです」"
  },
  {
    "name": "花",
    "message": "「そうです。何と言われようとやめませんよ」"
  },
  {
    "name": "奏命",
    "message": "「ふぅ……愛されすぎるのも辛いわね」"
  },
  {
    "name": "奏命",
    "message": "「あなたもよ、凪。あれくらいのプレッシャーに\r\n負けるとは何事なの？」"
  },
  {
    "name": "凪",
    "message": "「ハッハッハッハッハ！！」"
  },
  {
    "name": "奏命",
    "message": "「笑っても誤魔化せないわよ。はぁ」"
  },
  {
    "message": "溜息を吐く奏命の口元には、\r\nうっすらと笑みが浮かんでいる。"
  },
  {
    "name": "奏命",
    "message": "「あなたたちの考えは理解したわ。\r\nここまでされて強行するほど私も頑固じゃない」"
  },
  {
    "name": "奏命",
    "message": "「というわけで、凪。\r\n即刻私を惚れさせなさい」"
  },
  {
    "name": "凪",
    "message": "「俺が頑張る方向なのか」"
  },
  {
    "name": "奏命",
    "message": "「当然じゃない」"
  },
  {
    "name": "凪",
    "message": "「奏命が俺に惚れる努力をしてくれてもいいぞ」"
  },
  {
    "name": "奏命",
    "message": "「これ以上は無理よ」"
  },
  {
    "name": "凪",
    "message": "「左様ですか……」"
  },
  {
    "name": "奏命",
    "message": "「子作りはできるだけ早く始めたいし、\r\n時間を見つけてまたデートでもしましょうか」"
  },
  {
    "name": "奏命",
    "message": "「凪、来週の予定は？　休日はどうなってるの？」"
  },
  {
    "name": "凪",
    "message": "「今のところ全部空いてる」"
  },
  {
    "name": "奏命",
    "message": "「なるほどね……でもせっかくデートするなら、\r\n前回よりも驚きのある時間を過ごしてみたいわ」"
  },
  {
    "name": "奏命",
    "message": "「こちらでプランは練っておくから、\r\n土日を空けておいて頂戴」"
  },
  {
    "message": "用件だけ伝えて奏命はすぐに出て行ってしまった。"
  },
  {
    "message": "空と花を認めさせるのに積極的になってくれたのは、\r\nこちらとしては有難い限りだが……。"
  },
  {
    "name": "花",
    "message": "「……どういうプランを考えてるんですかねー、\r\n奏命様」"
  },
  {
    "name": "空",
    "message": "「せっかく勉強したのにね～」"
  },
  {
    "name": "凪",
    "message": "「でも、奏命の用意するプランってことは、\r\n奏命について知る機会でもある」"
  },
  {
    "name": "花",
    "message": "「おおっ、心強いお言葉っ！」"
  },
  {
    "name": "空",
    "message": "「問題はまだ実践を経験していないってとこだよね」"
  },
  {
    "name": "凪",
    "message": "「そこは俺の可愛さで乗り切るしかない」"
  },
  {
    "name": "花",
    "message": "「布波能くんが、可愛い……？」"
  },
  {
    "name": "空",
    "message": "「ちょっとわかんないね……」"
  },
  {
    "name": "凪",
    "message": "「俺もわからんが、奏命はよく言ってるぞ」"
  },
  {
    "name": "花",
    "message": "「そういう意味では\r\n進展していると捉えてもいい気がしますね」"
  },
  {
    "name": "空",
    "message": "「婚約者のひいき目ってやつだね」"
  },
  {
    "name": "凪",
    "message": "「つーか、進展してなかったら今頃、\r\n婚姻届を破り捨てて俺を追い出してるだろ」"
  },
  {
    "name": "花",
    "message": "「それは間違いありませんね」"
  },
  {
    "name": "空",
    "message": "「いい変化が奏命様に起きてるのは間違いない。\r\n布波能くん、もう一息だよっ！」"
  },
  {
    "name": "凪",
    "message": "「おう、任せとけっ！」"
  }
]