[
  {
    "message": "汐莉がその場を去ると、\r\nイヴはそっと立ち上がり歩き出した。"
  },
  {
    "message": "人の波をかき分け、俺はイヴを追いかける。"
  },
  {
    "name": "凪",
    "message": "「イヴッ！」"
  },
  {
    "name": "イヴ",
    "message": "「あ、凪……。ごめん、負けちゃった」"
  },
  {
    "message": "力なく、イヴが笑う。"
  },
  {
    "name": "凪",
    "message": "「…………」"
  },
  {
    "name": "イヴ",
    "message": "「えと……ここじゃ人目につくし、屋上にいこっか」"
  },
  {
    "message": "屋上の扉を開ける。"
  },
  {
    "message": "運動部総括の試合があったからか、ひと気はなかった。"
  },
  {
    "message": "まだ少しぼんやりしているイヴを、隣に座らせる。"
  },
  {
    "name": "凪",
    "message": "「さっき、謝ってたけどさ……。\r\nそんなこと言う必要ないって」"
  },
  {
    "name": "イヴ",
    "message": "「ううん、謝らないといけないよ」"
  },
  {
    "name": "イヴ",
    "message": "「あれだけ大口を叩いておいて\r\nあっさり負けちゃったんだからね」"
  },
  {
    "name": "イヴ",
    "message": "「せっかく凪の彼女になって初めての試合だったのに、\r\n情けない姿を見せちゃったなー」"
  },
  {
    "message": "いつもの調子を保とうとしているのが伝わってくるが、\r\nやはり声に元気がない。"
  },
  {
    "name": "凪",
    "message": "「情けないと思ったならやり直せばいいさ。\r\nイヴは努力の天才だろ？」"
  },
  {
    "name": "イヴ",
    "message": "「努力の天才かー……」"
  },
  {
    "name": "イヴ",
    "message": "「凪さ、私って本当にやり直せると思う？」"
  },
  {
    "name": "凪",
    "message": "「たった一回負けただけだろ？　弱気になるなって」"
  },
  {
    "name": "イヴ",
    "message": "「凪にはそう見えたかもしれないけど、\r\n私にとっては全然違う意味があったんだ」"
  },
  {
    "name": "イヴ",
    "message": "「どうして私に勝てたら運動部総括の座を譲るって\r\n形式にしたか分かる？」"
  },
  {
    "name": "凪",
    "message": "「そうだなー……努力の成果を確かめるためとか？」"
  },
  {
    "name": "凪",
    "message": "「イヴは努力を欠かさないから、\r\n定期的に強い相手と試合をする必要があったみたいな」"
  },
  {
    "name": "凪",
    "message": "「運動部総括っていう景品が懸かってたら、\r\n相手の気合も変わってくるだろうし」"
  },
  {
    "name": "イヴ",
    "message": "「んー、そういう意味もあったのかも」"
  },
  {
    "name": "イヴ",
    "message": "「私が運動部総括っていう座を守りたかった一番の理由\r\nは、自分の強さを肌で感じ続けたかったから」"
  },
  {
    "name": "イヴ",
    "message": "「ほら、運動部総括として勝ち続けている間は、\r\n自分は優れた人間だって証明出来るでしょ？」"
  },
  {
    "name": "凪",
    "message": "「身分証明書みたいな？」"
  },
  {
    "name": "イヴ",
    "message": "「そうそう、そんな感じ！」"
  },
  {
    "name": "イヴ",
    "message": "「努力をすればトップに立てる。努力は裏切らない。\r\nその事実が、私を支えてくれていた」"
  },
  {
    "name": "イヴ",
    "message": "「私の価値の裏付けでもあった。\r\n……なのに、なくなっちゃった」"
  },
  {
    "name": "凪",
    "message": "「やめろよ、もう諦めたみたいな言い方はさ」"
  },
  {
    "message": "困ったようにはにかみつつも、\r\n視線を合わせようとしない。"
  },
  {
    "name": "イヴ",
    "message": "「もちろん夢を捨てるつもりはないよ。\r\n凪との約束もあるしね」"
  },
  {
    "name": "イヴ",
    "message": "「ただ、汐莉に負けて、やっぱり自分は\r\n凡人なんだと再認識させられた」"
  },
  {
    "name": "イヴ",
    "message": "「まさかこんな短期間に追い抜かれちゃうなんて、\r\n嫌になっちゃうよ……」"
  },
  {
    "name": "イヴ",
    "message": "「ううん、違う。\r\nいずれこの時が来るのはわかってたの」"
  },
  {
    "name": "イヴ",
    "message": "「圧倒的な才能を持つものと戦えば、私は負ける。\r\nその時にまた、立ち上がれるかどうか……」"
  },
  {
    "name": "イヴ",
    "message": "「努力は好き。でも、やっぱり……、\r\n努力って苦しいよ……」"
  },
  {
    "name": "イヴ",
    "message": "「どうして私には才能がないんだろ。\r\n才能があれば、もっと上手にできたかもしれない」"
  },
  {
    "name": "イヴ",
    "message": "「恋のせいでダメになったなんて、\r\n絶対に言わせなかったのに……」"
  },
  {
    "name": "凪",
    "message": "「俺はイヴみたいに努力してこなかったから、\r\n……多分、イヴの気持ちがわかってない」"
  },
  {
    "name": "凪",
    "message": "「だけど、またやり直せるかっていう質問には\r\n答えられる」"
  },
  {
    "name": "凪",
    "message": "「イヴは、絶対に運動部総括へ返り咲く。\r\n勝ちたいと本当に望むならな」"
  },
  {
    "name": "凪",
    "message": "「やりたくないならいいよ。やめちまえ。\r\n汐莉に任せて引退だ」"
  },
  {
    "name": "凪",
    "message": "「誰が何を言ってきても、俺が守ってやる」"
  },
  {
    "message": "イヴは目を閉じ、静かに首を横に振った。"
  },
  {
    "name": "イヴ",
    "message": "「ううん。負けっぱなしは嫌。\r\n運動部総括の座は諦めない」"
  },
  {
    "name": "凪",
    "message": "「おし、なら一緒に頑張ろうぜ！」"
  },
  {
    "name": "イヴ",
    "message": "「ありがとうね……凪がいて本当に良かったよ」"
  },
  {
    "name": "イヴ",
    "message": "「前までの私だったら多分挫けていたと思う。\r\n凪は私のヒーローだね」"
  },
  {
    "name": "凪",
    "message": "「んな訳あるか！　どこからどう見ても\r\n正義のヒーローには見えないだろ」"
  },
  {
    "name": "イヴ",
    "message": "「じゃあダークヒーロー？」"
  },
  {
    "name": "凪",
    "message": "「うーん……ヒーローは無しで。\r\n俺はただのイヴの彼氏だ」"
  },
  {
    "name": "イヴ",
    "message": "「ふふっ、それが一番嬉しい言葉かもしれないね」"
  },
  {
    "message": "とりあえず言いたかったことは伝えられた。"
  },
  {
    "message": "イヴの諦めないという意志を知れただけで十分だ。\r\nこれでやるべきことは定まったからな。"
  },
  {
    "message": "そして、この場所に俺はもういるべきじゃない。"
  },
  {
    "name": "凪",
    "message": "「冷えてきたし、俺は部屋に戻るけど\r\nイヴはどうする？」"
  },
  {
    "name": "イヴ",
    "message": "「私はもう少しだけここにいるかな。\r\nわざわざ追いかけてきてくれてありがとうね」"
  },
  {
    "name": "凪",
    "message": "「何言ってるんだ、当たり前だろ」"
  },
  {
    "name": "凪",
    "message": "「風邪を引いても良くないから、\r\nほどほどにしておくんだぞ」"
  },
  {
    "name": "イヴ",
    "message": "「うん！　また明日からよろしくね」"
  },
  {
    "message": "屋上の扉を閉め、俺は壁にもたれかかる。"
  },
  {
    "message": "イヴが座っているのは、壁を挟んだすぐのところだ。"
  },
  {
    "message": "しばらくそうしていると、微かな音が聞こえ始めた。"
  },
  {
    "name": "イヴ",
    "message": "「うぅっ、ぐすっ……すん、ぐずっ…………」"
  },
  {
    "message": "……無事でいられるはずがないんだよな。"
  },
  {
    "message": "大切なものを奪われて平然としていられるほど、\r\n人間は単純な生き物じゃない。"
  },
  {
    "message": "今は俺が傍にいるよりも、一人の時間が必要だろう。"
  },
  {
    "message": "そしてきっとイヴなら\r\n自分の足で立ち上がれると信じている。"
  },
  {
    "message": "運動部総括決定戦の翌日。\r\n俺は学生会室に繋がる廊下で突っ立っていた。"
  },
  {
    "message": "現在この部屋の中では、運動部総括の座の譲渡が\r\n行われているらしい。"
  },
  {
    "message": "そこまではいいんだが、何故か部外者である俺も\r\n呼び出しをくらっていた。"
  },
  {
    "message": "今は譲渡が終わるまで、途中で捕まえたファイブと\r\n雑談して時間を潰しているところだった。"
  },
  {
    "name": "ファイブ",
    "message": "「あれからイウヴァリー様の様子はいかがですの」"
  },
  {
    "name": "凪",
    "message": "「本人の心境がどんなものかは分からないけど、\r\nとくに目立った変化はないな」"
  },
  {
    "name": "ファイブ",
    "message": "「そうですの……イウヴァリー様は大丈夫でしょうか」"
  },
  {
    "name": "ファイブ",
    "message": "「私も見ていましたが、衆目に晒されている中で、\r\nあの仕打ちは見るに堪えないものがありました」"
  },
  {
    "name": "ファイブ",
    "message": "「心に負った傷がどれほど深いものであるのか、\r\n私には想像もつきませんの」"
  },
  {
    "name": "凪",
    "message": "「…………まぁな」"
  },
  {
    "name": "凪",
    "message": "「だけど、いくら傷が深くてもイヴなら立ち直れる。\r\n少なくとも俺はそう信じている」"
  },
  {
    "name": "凪",
    "message": "「このまま潔く諦めるような人間じゃないさ」"
  },
  {
    "name": "ファイブ",
    "message": "「そちらも心配ですが、個人的には凪様の方も\r\n心配ですの」"
  },
  {
    "name": "ファイブ",
    "message": "「あの件はイウヴァリー様が傷つけられただけではなく\r\n凪様の負担にもなっているはずですの」"
  },
  {
    "name": "ファイブ",
    "message": "「ですからあまり無理はせずにご自愛くださいませ」"
  },
  {
    "name": "凪",
    "message": "「わかってるよ。ありがとな」"
  },
  {
    "message": "ファイブとの話が一区切りついたと同時に学生会室の\r\n扉が開く。"
  },
  {
    "message": "用件を終えたであろう汐莉はこちらを一瞥して、\r\nニコリと微笑んだ。"
  },
  {
    "name": "汐莉",
    "message": "「心配しなくても、ちゃーんともらいましたよ？」"
  },
  {
    "message": "ただそれだけの言葉を残して行ってしまった。"
  },
  {
    "message": "追いかけて、引き留めたかったがそれよりも早く、\r\nスピーカーで名前を呼ばれる。"
  },
  {
    "name": "奏命",
    "message": "「凪、入りなさい」"
  },
  {
    "message": "俺は話し相手になってくれていたファイブと別れて、\r\n学生会室へ入室した。"
  },
  {
    "message": "一歩足を踏み入れた時、重苦しい空気が漂っているのを\r\n察知する。"
  },
  {
    "message": "新しい運動部総括の誕生。\r\n桜元学園の生徒会としては喜ぶべきことなんだろう。"
  },
  {
    "message": "だが、この場では誰もが祝い事と捉えていないのが\r\n俺にとっては嬉しかった。"
  },
  {
    "name": "奏命",
    "message": "「本日を以ってイヴから運動部総括の役職を引継ぎ、\r\n大屋汐莉がその席に座ることになったわ」"
  },
  {
    "name": "凪",
    "message": "「大丈夫だ、言われなくても分かってる」"
  },
  {
    "name": "奏命",
    "message": "「もう受け入れてはいるのね」"
  },
  {
    "name": "凪",
    "message": "「わざわざそんな確認のために俺を呼んだのか？」"
  },
  {
    "name": "奏命",
    "message": "「まさか。あなたを呼んだのは指導の件があったから」"
  },
  {
    "name": "奏命",
    "message": "「あなたの指導をイヴが担当していたのは、\r\n彼女が運動部総括だったから」"
  },
  {
    "name": "奏命",
    "message": "「残念だけど、今のイヴに指導の資格はない」"
  },
  {
    "name": "奏命",
    "message": "「指導が必要であれば私たちのどちらかが\r\n引き継ぐけど、どうしましょうか？」"
  },
  {
    "name": "凪",
    "message": "「イヴはすぐに運動部総括に戻る。\r\nだから変更の必要はない」"
  },
  {
    "name": "奏命",
    "message": "「わかったわ。\r\n……ちなみにイヴの様子はどう？」"
  },
  {
    "name": "凪",
    "message": "「大丈夫、だと思う」"
  },
  {
    "name": "凪",
    "message": "「ただ喪失した自信を取り戻すまでは\r\n時間がかかるかもしれないな」"
  },
  {
    "name": "くくる",
    "message": "「そう。それなら安心した」"
  },
  {
    "name": "くくる",
    "message": "「自信を取り戻す方法は簡単。\r\n負けた相手に勝てばいいだけ」"
  },
  {
    "name": "凪",
    "message": "「ああ、俺もそう思う……それが一番だ」"
  },
  {
    "name": "くくる",
    "message": "「私情を挟むべきじゃないけど、\r\nわたしはあの大屋って子は好きになれそうにない」"
  },
  {
    "name": "くくる",
    "message": "「イヴに運動部総括に戻ってほしい」"
  },
  {
    "name": "奏命",
    "message": "「ふふっ、くくるは本当に素直ね」"
  },
  {
    "name": "くくる",
    "message": "「会長だってそう思ってるんじゃないの？」"
  },
  {
    "name": "奏命",
    "message": "「好き嫌いを言葉にしていい立場ではないもの。\r\n桜元学園という組織を第一に考えるのが私の役目」"
  },
  {
    "name": "奏命",
    "message": "「……けれど、運動部総括として頑張るイヴのことは\r\n好きだったと言っておこうかしら」"
  },
  {
    "name": "くくる",
    "message": "「もうイヴの方が良かったって言ってる気がする」"
  },
  {
    "name": "奏命",
    "message": "「あら、大屋汐莉については\r\n何も言及していないけれど？」"
  },
  {
    "message": "さっきまでの張りつめていた空気が霧散する。"
  },
  {
    "message": "俺だけじゃない、やっぱり皆がイヴに\r\n戻って来てほしがっているんだ。"
  },
  {
    "message": "ここでの話は今度イヴに伝えるべきかな。"
  },
  {
    "message": "しばらくは学生会へ来る機会もないだろうし、\r\n喜んでくれそうだ。"
  },
  {
    "name": "くくる",
    "message": "「わたしはイヴがここへ帰って来るのを待ってる。\r\nそのためなら協力も惜しまないからよろしく」"
  },
  {
    "name": "凪",
    "message": "「ああ、折を見て伝えておくよ」"
  },
  {
    "message": "学生会の二人がイヴを待っている。"
  },
  {
    "message": "そのことを知れば、\r\nイヴも少しは自信を取り戻すだろう。"
  },
  {
    "message": "このメンバーで話す機会を作ってくれたことに\r\n感謝しつつ、俺は学生会室を後にした。"
  }
]