[
  {
    "message": "試合の後、汐莉の意識が戻ってから\r\n俺たち三人は中庭に集合した。"
  },
  {
    "message": "ここに集まったのは他でもない。\r\n事前に話していた約束を果たしてもらうためだ。"
  },
  {
    "name": "イヴ",
    "message": "「約束通り、話は聞かせてもらえるんだよね？」"
  },
  {
    "name": "汐莉",
    "message": "「……負けちゃったしね。別にいいよ」"
  },
  {
    "name": "汐莉",
    "message": "「確かあんたに近付いた動機と運動部総括を懸けて\r\n戦った理由だったよね」"
  },
  {
    "name": "汐莉",
    "message": "「正直なところ、ボクは運動部総括なんて\r\nどうでも良かったんだ」"
  },
  {
    "name": "汐莉",
    "message": "「あんたに勝ちたかった。それだけ」"
  },
  {
    "name": "イヴ",
    "message": "「……どうして？」"
  },
  {
    "name": "イヴ",
    "message": "「汐莉はどうしてそこまで私に執着するの？」"
  },
  {
    "name": "イヴ",
    "message": "「自分にある無限の可能性を捨ててまで、\r\n私を不幸にする意味はあるの？」"
  },
  {
    "name": "イヴ",
    "message": "「理由あるなら私だって協力するよ。\r\nだから話してくれないかな……？」"
  },
  {
    "name": "汐莉",
    "message": "「…………っ」"
  },
  {
    "name": "汐莉",
    "message": "「……協力出来ることなんて何もないよ」"
  },
  {
    "name": "イヴ",
    "message": "「そんなことない」"
  },
  {
    "name": "汐莉",
    "message": "「無理だよ」"
  },
  {
    "name": "汐莉",
    "message": "「だってボクたちの生まれ方を変えてなんて言っても\r\nどうにも出来ないでしょ？」"
  },
  {
    "name": "凪",
    "message": "「生まれ方？　……なんの話をしてるんだ？」"
  },
  {
    "name": "汐莉",
    "message": "「…………血が繋がってるんだ」"
  },
  {
    "name": "汐莉",
    "message": "「ボクはイヴ先輩の腹違いの妹なんだ。\r\n今も警察庁長官という立場にいるあの人の」"
  },
  {
    "name": "イヴ",
    "message": "「えっ…………ちょっと待って、そんな……」"
  },
  {
    "name": "イヴ",
    "message": "「だって私はそんな話聞いたこともないし、\r\n妹がいたなんて周りからも……」"
  },
  {
    "name": "汐莉",
    "message": "「そりゃ、誰にも言えないよ。\r\n立場のある人なんだから」"
  },
  {
    "name": "汐莉",
    "message": "「ひどい扱いは受けてないから安心して。\r\n養育費も残してくれてる」"
  },
  {
    "name": "汐莉",
    "message": "「あの人の愛とかそういう類のものは、\r\n母さんしかもらってないけどね」"
  },
  {
    "name": "凪",
    "message": "「……汐莉の母さんは今はどこに？」"
  },
  {
    "name": "汐莉",
    "message": "「もう、いないよ。ずっと前に病気で亡くなった」"
  },
  {
    "name": "汐莉",
    "message": "「苦労自慢するつもりはないけど。\r\nそれからずっと、ボクは一人で生きてきたんだ」"
  },
  {
    "name": "イヴ",
    "message": "「…………」"
  },
  {
    "message": "イヴが悪い訳ではない……だが、どうすればいいか\r\n分からなかったんだろう。"
  },
  {
    "message": "幼心に宿した憎しみの芽は、イヴの不幸を求め、\r\n汐莉を暴走させるほどに、心の深くまで根を下ろした。"
  },
  {
    "name": "汐莉",
    "message": "「そんな顔しなくていいよ。\r\nあの人のことは恨んでない」"
  },
  {
    "name": "汐莉",
    "message": "「ただね、一人になったせいかな。\r\n拠り所がなくなっちゃったんだ」"
  },
  {
    "name": "イヴ",
    "message": "「お父さんは汐莉が一人になったこと、知ってたの？」"
  },
  {
    "name": "汐莉",
    "message": "「知らないんじゃないかな」"
  },
  {
    "name": "汐莉",
    "message": "「もう二度と会わない。\r\nそういう約束をしたって母さんが言ってたし」"
  },
  {
    "name": "汐莉",
    "message": "「葬式にも来なかったから」"
  },
  {
    "name": "汐莉",
    "message": "「それで寂しさをこじらせたボクは、\r\nあなたに近づいてみたわけです」"
  },
  {
    "name": "汐莉",
    "message": "「あなたに勝ってあの人に見つけてほしかったのか、\r\n捨てた子供のほうが優秀だとわからせたかったのか」"
  },
  {
    "name": "汐莉",
    "message": "「そのあたりはぐちゃぐちゃで、\r\nボクにもよくわかんないですけど……」"
  },
  {
    "name": "汐莉",
    "message": "「近づいたせいで、\r\nイヴ先輩のこと好きになっちゃった」"
  },
  {
    "name": "汐莉",
    "message": "「もちろん、友愛的な意味ですけど。\r\nいや、この場合は家族愛って言った方がいいのかな」"
  },
  {
    "name": "汐莉",
    "message": "「このまま何もなかったことにしよう。\r\nそう考えていた時に現れたのが……」"
  },
  {
    "message": "汐莉の視線が俺に向けられる。"
  },
  {
    "name": "汐莉",
    "message": "「布波能先輩ってば、\r\nすぐにイヴ先輩と仲良くなってさ」"
  },
  {
    "name": "汐莉",
    "message": "「イヴ先輩もイヴ先輩で、鍛錬の頻度下げるし」"
  },
  {
    "name": "汐莉",
    "message": "「イヴ先輩はそんな人じゃないってわかってたのに、\r\nどうしても考えるのを止められなかったんです」"
  },
  {
    "name": "汐莉",
    "message": "「結局本命ができれば、\r\nボクも武術もあっけなく捨てられるんだ」"
  },
  {
    "name": "汐莉",
    "message": "「ボクは母さんと同じ。用が済んだら関係は終わり。\r\n最悪なかったことにされる」"
  },
  {
    "name": "汐莉",
    "message": "「そう思ったら……」"
  },
  {
    "name": "汐莉",
    "message": "「薄れたはずの黒い気持ちがまたこみあげてきて、\r\nだんだん抑えられなくなって……」"
  },
  {
    "name": "汐莉",
    "message": "「どうにかして嫌な気持ちをなくしたかったんです。\r\nだから最初の目的を遂げることにした」"
  },
  {
    "name": "汐莉",
    "message": "「イヴ先輩の肩書きを奪って、運動部総括になって……\r\nきっと何かが変わるんだと信じてた」"
  },
  {
    "name": "汐莉",
    "message": "「でも……何もなかった。何も起きなかった」"
  },
  {
    "name": "汐莉",
    "message": "「それどころか、あったはずの居場所もなくなって……\r\nこれからどう生きていけばいいのかも分からなくて」"
  },
  {
    "message": "まるで助けを求めるような視線をイヴへ向けている汐莉。"
  },
  {
    "message": "言葉の通り、本人もどうすればいいのか\r\n分からないといった様相だった。"
  },
  {
    "message": "そんな汐莉に向けてイヴは寄り添う。"
  },
  {
    "name": "イヴ",
    "message": "「……話してくれてありがとうね、汐莉」"
  },
  {
    "name": "イヴ",
    "message": "「確かに私は凪のことが一番大切かもしれない」"
  },
  {
    "name": "イヴ",
    "message": "「だから改めてここに誓わせてもらう。\r\n私は何があっても汐莉の隣にいる」"
  },
  {
    "name": "汐莉",
    "message": "「隣に…………本当？」"
  },
  {
    "name": "イヴ",
    "message": "「うん、絶対に本当だよ」"
  },
  {
    "name": "汐莉",
    "message": "「じゃあ例えば布波能先輩がボクを許さないって\r\n言ってきたら？」"
  },
  {
    "name": "イヴ",
    "message": "「あ、あはは……これはまさかの質問だなー」"
  },
  {
    "name": "イヴ",
    "message": "「でも、私が好きになった人が、\r\n大切な後輩をないがしろにするはずないよ」"
  },
  {
    "name": "イヴ",
    "message": "「あとね、今よりも汐莉と仲良くなるために、\r\n一緒にしたいことがあるの」"
  },
  {
    "name": "イヴ",
    "message": "「今度二人でお父さんを懲らしめに行こうよ」"
  },
  {
    "name": "汐莉",
    "message": "「えっ……？」"
  },
  {
    "name": "イヴ",
    "message": "「不倫なんて警察庁長官として許されない行為だよ。\r\n私だって汐莉の話を聞いて怒ってるんだからね」"
  },
  {
    "name": "イヴ",
    "message": "「それにこんなに可愛い妹がいるって\r\n教えてくれなかったことにも罰を与えないとね」"
  },
  {
    "name": "汐莉",
    "message": "「……ううん、ダメだよ。\r\nそんなことしたって何も変わらない」"
  },
  {
    "name": "汐莉",
    "message": "「それにボクはもう……、自分があの人のことを\r\nどう思ってるのかすらもわからない」"
  },
  {
    "name": "イヴ",
    "message": "「あたりまえだよ。だけど、それでいい。\r\nその上でちゃんと話をしよう」"
  },
  {
    "name": "汐莉",
    "message": "「だけど、こわいよ……そんなことをしたら、\r\nきっとボクはあなたから引き離される」"
  },
  {
    "name": "汐莉",
    "message": "「また一人になるのは、嫌だ……」"
  },
  {
    "name": "イヴ",
    "message": "「弱気になっちゃダメだよ。\r\n何があっても私が守るって約束する」"
  },
  {
    "name": "イヴ",
    "message": "「先輩としてでも、姉としてでもいい」"
  },
  {
    "name": "イヴ",
    "message": "「辛いことがあればいつでも相談に乗るし、\r\n不満があれば今度は正面から言ってくれると嬉しい」"
  },
  {
    "name": "イヴ",
    "message": "「私はどんな汐莉も嫌いにならないよ」"
  },
  {
    "name": "イヴ",
    "message": "「私を慕ってくれた明るい汐莉も、今みたいに\r\n弱気になってる汐莉も、さっきまでのわるーい汐莉も全部ね」"
  },
  {
    "name": "汐莉",
    "message": "「…………ぐすっ、ありがとう、イヴ先輩」"
  },
  {
    "message": "イヴが差し出した手は振り払われることなく固く\r\n結ばれた。"
  },
  {
    "message": "これで一件落着、ハッピーエンドってところかな。"
  },
  {
    "name": "イヴ",
    "message": "「うーん…………」"
  },
  {
    "message": "……なのに仲直りしたはずの姉は何故か唸っていた。"
  },
  {
    "name": "イヴ",
    "message": "「よく考えたら私は汐莉から酷いことをされたんだから\r\nこれから仲良くする上でけじめは付けるべきだと思う」"
  },
  {
    "name": "凪",
    "message": "「運動部総括の座を奪われたのには\r\n納得してたんじゃないのか？」"
  },
  {
    "name": "イヴ",
    "message": "「それじゃなくて凪にキスしたことだよ」"
  },
  {
    "name": "凪",
    "message": "「そっちかい！？」"
  },
  {
    "name": "イヴ",
    "message": "「凪からすれば汐莉とキス出来て役得だったのかも\r\nしれないけど、彼女の私からしたら……ねぇ？」"
  },
  {
    "name": "凪",
    "message": "「ねぇ？　って言われてもさ……」"
  },
  {
    "name": "イヴ",
    "message": "「汐莉はどう？　けじめを付けて今までのことは\r\n綺麗さっぱり水に流す！　これでどうかな」"
  },
  {
    "name": "汐莉",
    "message": "「ボクはイヴ先輩に酷いことをした側だから、\r\nそれで許してくれるなら……」"
  },
  {
    "name": "イヴ",
    "message": "「うん、分かった！　じゃあこれからは私のことを\r\nお姉ちゃんって呼んでね！」"
  },
  {
    "name": "汐莉",
    "message": "「…………え？　いや、でも……\r\nボクたちの関係は口外できるものじゃないし」"
  },
  {
    "name": "イヴ",
    "message": "「私と凪の前にいるときだけでいいよっ！」"
  },
  {
    "name": "汐莉",
    "message": "「だけど、もうイヴ先輩って呼び慣れてるし、\r\n今さら変えろって言われても……」"
  },
  {
    "name": "イヴ",
    "message": "「お姉ちゃんって呼んでね！」"
  },
  {
    "name": "汐莉",
    "message": "「……出来れば他の方法を考えてほしいっていうか」"
  },
  {
    "name": "イヴ",
    "message": "「ダメです、これしか方法がありません」"
  },
  {
    "name": "イヴ",
    "message": "「お姉ちゃんって呼ぶだけでしょ？\r\n何がそんなに嫌なのさー」"
  },
  {
    "name": "汐莉",
    "message": "「今さら恥ずかしいのを分かってよ！\r\nイヴ先輩のままでも困らないし！」"
  },
  {
    "name": "イヴ",
    "message": "「ダメです、この儀式をしないと\r\nこれから仲良く出来る気がしません」"
  },
  {
    "name": "イヴ",
    "message": "「汐莉は今この瞬間に生まれ変わるんだよ、\r\n私の可愛い妹としてね！」"
  },
  {
    "name": "イヴ",
    "message": "「妹が姉のことをお姉ちゃんって呼ぶのは当たり前！\r\n何も恥ずかしくなんてないの！」"
  },
  {
    "name": "凪",
    "message": "「テンション高いっすね……」"
  },
  {
    "message": "イヴはこういう時、絶対に譲らないと俺は知っている。"
  },
  {
    "message": "汐莉も同じことを考えていたのか、\r\nどうやら観念したようだ。"
  },
  {
    "name": "汐莉",
    "message": "「分かったよ！　呼べばいいんでしょ、呼べばっ！」"
  },
  {
    "name": "汐莉",
    "message": "「おねっ……おね、お姉ちゃん……」"
  },
  {
    "name": "イヴ",
    "message": "「今なんて言ったの、風が吹いて聞こえなかった」"
  },
  {
    "name": "汐莉",
    "message": "「風なんて吹いてなかった！\r\n絶対に聞こえたに決まってる！」"
  },
  {
    "name": "イヴ",
    "message": "「いいでしょ、もう一回だけ呼んでみてよー」"
  },
  {
    "name": "汐莉",
    "message": "「～～～っ！　お姉ちゃんお姉ちゃんお姉ちゃん！\r\nもうこれで満足！？」"
  },
  {
    "name": "イヴ",
    "message": "「おおっ、一回で良かったのに大サービスだね」"
  },
  {
    "name": "汐莉",
    "message": "「はぁ……イヴ先輩はたまにいたずらをしたがるよね」"
  },
  {
    "name": "イヴ",
    "message": "「イヴ先輩って誰だろう、私は知らないなー」"
  },
  {
    "name": "汐莉",
    "message": "「お姉ちゃんっ！！」"
  },
  {
    "message": "こんなに騒がしくてもふざけた雰囲気でも二人には\r\n特別なやり取りだったんだと思う。"
  },
  {
    "message": "何しろ姉妹として初めてお互いを認識した瞬間でも\r\nあるんだからな。"
  },
  {
    "message": "雲間から溢れる日の光が、紡がれた絆を祝福するように\r\n姉妹を照らす。"
  },
  {
    "message": "この二人にはいつまでも幸せが続く。\r\nそう確信させられるような光景だった。"
  }
]