[
  {
    "message": "イヴが恋人になったことで、\r\n多少は生活に変化が起きるものだと思っていた。"
  },
  {
    "message": "俺の主張を誰もが理解してくれるわけじゃない。"
  },
  {
    "message": "ファンの連中や周囲の人間は何かしらアクションを\r\n起こすはずだ。"
  },
  {
    "message": "そう考えて、俺は警戒していたのだが……。"
  },
  {
    "name": "イヴ",
    "message": "「なーぎー！　これから一緒にカフェでもどう？」"
  },
  {
    "name": "凪",
    "message": "「放課後になった瞬間に来たな……」"
  },
  {
    "name": "凪",
    "message": "「ここ最近、毎日だけど、学生会の方は大丈夫なのか？」"
  },
  {
    "name": "イヴ",
    "message": "「会長からも定期報告だけ出席するという内容で了承を\r\n貰ってるよ。私は凪の指導役だからね」"
  },
  {
    "name": "イヴ",
    "message": "「いつでもどこでも凪と一緒にいられるよ」"
  },
  {
    "name": "凪",
    "message": "「それは俺としても望むところなんだけどさ、\r\nあまりにもベタベタとしすぎだろ」"
  },
  {
    "name": "イヴ",
    "message": "「えぇー、私たち付き合ってるんだから、\r\nどこに問題があるっていうのさ」"
  },
  {
    "name": "凪",
    "message": "「別に問題はないんだろうけど、\r\n人目ってもんがあるだろ」"
  },
  {
    "name": "イヴ",
    "message": "「見せつけちゃうのも悪くないよねー」"
  },
  {
    "name": "イヴ",
    "message": "「周りにも凪が二股する人なんかじゃないって\r\n証明してあげないと」"
  },
  {
    "name": "凪",
    "message": "「俺の話をちゃんと聞いてたか！？」"
  },
  {
    "message": "内心では薄々気付いている。"
  },
  {
    "message": "俺がなんと言ったって、イヴがベタベタしてくるのを\r\n止めるとは思ってはいない。"
  },
  {
    "message": "恐らくイヴも同じように、何かしらのアクションが\r\n起こるのを警戒しているに違いない。"
  },
  {
    "message": "その上で俺に被害を及ばせないように\r\n主張しているのだ。"
  },
  {
    "message": "布波能凪は蓼科イヴの男なのだと。"
  },
  {
    "name": "凪",
    "message": "「カフェに行くのもいいが、\r\n最近はサボっちゃってるし、今日は勉強をしたい」"
  },
  {
    "name": "イヴ",
    "message": "「じゃあそうしようか、本音を言っちゃうと私は凪と\r\n一緒にいられればなんでもいいし」"
  },
  {
    "name": "凪",
    "message": "「よくできた恋人だ……、\r\nじゃあ付き合ってもらうぞ」"
  },
  {
    "name": "イヴ",
    "message": "「もう付き合ってるんだけど？」"
  },
  {
    "name": "凪",
    "message": "「図書館にだよっ！\r\nいちいちそっちの話に持っていこうとするな！」"
  },
  {
    "message": "それからというもの、\r\n俺たちはいつでも二人で行動するようになった。"
  },
  {
    "message": "今では、指導役として傍にいてくれた頃よりも\r\n遥かに長い時間を共有している。"
  },
  {
    "message": "そんな風に過ごしているのが学生たちの目に入らない\r\nはずがなく、いつの間にか二股の噂は聞かなくなった。"
  },
  {
    "message": "おかげでいざこざも起きず、最近はファンからの呪詛が\r\n聞こえてくるだけの至って平和な日々を過ごせている。"
  },
  {
    "message": "気になるのは最近、\r\n汐莉の姿を見かけなくなったということだ。"
  },
  {
    "message": "イヴも汐莉のことは気にかけているようだが、\r\n俺と同じく避けられているらしい。"
  },
  {
    "message": "どうしてあんなことをしたのかと\r\n理由を聞くべきなのはわかっている。"
  },
  {
    "message": "だが、汐莉がその気にならなければ\r\n本心を聞くことはできないだろう。"
  },
  {
    "message": "それならば考えても仕方がない。"
  },
  {
    "message": "今はイヴとの学生生活を謳歌しつつ\r\nその時が来るのを待つとしよう。"
  },
  {
    "name": "イヴ",
    "message": "「なーぎー！　お弁当作ってきたから屋上で一緒に\r\n食べようよー」"
  },
  {
    "name": "凪",
    "message": "「おぉー……どこにも逃げないんだから\r\nそんなに急いで来なくてもいいんだぞ」"
  },
  {
    "name": "イヴ",
    "message": "「そういう問題じゃなくてー」"
  },
  {
    "name": "イヴ",
    "message": "「一刻も早く凪に会いたいっていう\r\nこの乙女心が分からないかな」"
  },
  {
    "name": "凪",
    "message": "「乙女ではないけど分かってるつもりだぞ」"
  },
  {
    "name": "イヴ",
    "message": "「本当かな？　その割には凪の方から私に会いに\r\n来てくれたことってないよね」"
  },
  {
    "name": "凪",
    "message": "「それはその、何だ……」"
  },
  {
    "name": "凪",
    "message": "「他のクラスに行ったことなんてないし、\r\n変な目で見られるだろ」"
  },
  {
    "name": "イヴ",
    "message": "「……本当は自分から会いに来て、\r\n恋人らしく振る舞うのが恥ずかしかったり？」"
  },
  {
    "name": "イヴ",
    "message": "「もぉー、凪ってそういうところあるから\r\n可愛いんだよね！」"
  },
  {
    "name": "凪",
    "message": "「うるさい！\r\n用意するから先に廊下に出て待っててくれ」"
  },
  {
    "name": "イヴ",
    "message": "「はぁーい」"
  },
  {
    "message": "授業で使った教材をしまい腰を上げたところで\r\nテイオーと目が合った。"
  },
  {
    "name": "凪",
    "message": "「何も言わないでくれ……」"
  },
  {
    "name": "帝雄",
    "message": "「君たちの仲が微笑ましいだけだよ」"
  },
  {
    "name": "帝雄",
    "message": "「蓼科さんも凪くんと付き合い始めてから、\r\n随分と変わったよね」"
  },
  {
    "name": "凪",
    "message": "「変わったというより、\r\nあれはただ遠慮をしなくなっただけだ」"
  },
  {
    "name": "帝雄",
    "message": "「その違いが僕にはわからないけど、\r\nいい変化のように見える」"
  },
  {
    "name": "凪",
    "message": "「そう言ってもらえると嬉しいよ」"
  },
  {
    "name": "イヴ",
    "message": "「なーぎー。まーだー？」"
  },
  {
    "name": "凪",
    "message": "「いま行く！　悪いな、せわしなくて」"
  },
  {
    "name": "帝雄",
    "message": "「気にしないで。楽しんできてね」"
  },
  {
    "message": "屋上に到着すると、\r\nイヴは空いているベンチに腰かけた。"
  },
  {
    "name": "イヴ",
    "message": "「今日のお昼はこれだよ」"
  },
  {
    "name": "凪",
    "message": "「サンドイッチ、だな」"
  },
  {
    "name": "イヴ",
    "message": "「その通り。凪がいつもサンドイッチばかり\r\n食べてるのを見ててライバル心が燃えてきちゃって」"
  },
  {
    "name": "凪",
    "message": "「ライバル心って誰に？」"
  },
  {
    "name": "イヴ",
    "message": "「厨房にいる料理長とか？」"
  },
  {
    "name": "凪",
    "message": "「俺の彼女は一体どこへ向かおうとしてるんだ……」"
  },
  {
    "name": "イヴ",
    "message": "「だって凪がいつも美味しそうに食べてるから。\r\n私にも作れるんだぞーって気になっちゃって」"
  },
  {
    "name": "イヴ",
    "message": "「あと、恋人の胃袋をつかむのは恋愛の基本でしょ？」"
  },
  {
    "message": "さすがは飽くなき向上心を併せ持つ\r\nイヴといったところか。"
  },
  {
    "message": "料理というジャンルでも\r\n強大な相手に立ち向かう姿勢は嫌いじゃない。"
  },
  {
    "name": "イヴ",
    "message": "「ささっ、口に合うかは分からないけどさっそく\r\n食べてみてよ」"
  },
  {
    "name": "イヴ",
    "message": "「でも、ただ食べてもらうのも味気ないかな。\r\nどうせならこうしてみよっか」"
  },
  {
    "message": "瞳を輝かせながら一切れのサンドイッチを手に取り、\r\nこちらへ向けてくる。"
  },
  {
    "name": "イヴ",
    "message": "「お口を開けて、はいどうぞ♪」"
  },
  {
    "name": "凪",
    "message": "「これは俗に言うあーんというやつか……？」"
  },
  {
    "name": "イヴ",
    "message": "「そうそう！　一度やってみたかったんだよね。\r\n早く口を開けて」"
  },
  {
    "name": "凪",
    "message": "「……あーん」"
  },
  {
    "name": "イヴ",
    "message": "「あーんっ♪　あぁ、このお世話してる感覚は\r\n癖になっちゃうかも」"
  },
  {
    "message": "イヴの恍惚とした声を聞きながら\r\nサンドイッチを咀嚼する。"
  },
  {
    "message": "まずはマスタードの香りが鼻を抜けた。"
  },
  {
    "message": "次第にベーコンと卵が自己主張を始め、\r\n続いてレタスのシャキシャキとした食感と瑞々しさが\r\n後味を爽やかにする。"
  },
  {
    "name": "凪",
    "message": "「これは……うん、かなり美味いな！」"
  },
  {
    "name": "イヴ",
    "message": "「お気に召してもらえたんだ、嬉しいなあ！」"
  },
  {
    "name": "イヴ",
    "message": "「ほら、たくさん作って来たからもっと食べてよ。\r\n私も食べてみようっと」"
  },
  {
    "message": "作った本人も一口食べて顔をほころばせたことから、\r\nかなり満足のいく出来だったようだ。"
  },
  {
    "message": "イヴのサンドイッチは初めて食べたが、\r\n具材の一つ一つに手間をかけられているのがよく分かる。"
  },
  {
    "message": "これからさらに腕を上げるのかもしれないと\r\n考えるだけで、楽しみになってくるというものだ。"
  },
  {
    "name": "凪",
    "message": "「イヴはなんでも上手に作るな。\r\n食堂のと比べても遜色ない。むしろそれ以上かも」"
  },
  {
    "name": "イヴ",
    "message": "「えー、それは褒めすぎじゃない？」"
  },
  {
    "name": "イヴ",
    "message": "「凪の好みも覚えたいから、\r\n苦手な味付けがあったら遠慮なくいってね」"
  },
  {
    "message": "好きな料理を作ってもらえる。\r\nかなり贅沢な提案だ。"
  },
  {
    "name": "凪",
    "message": "「でも、作るのも大変だろ？」"
  },
  {
    "name": "凪",
    "message": "「好みの食事ばかり作られたら\r\n舌が肥えてきそうだし、無理しなくていいんだぞ」"
  },
  {
    "name": "イヴ",
    "message": "「さっき言ったでしょ？\r\n私は凪の胃袋を掴みたいって」"
  },
  {
    "name": "イヴ",
    "message": "「ちょっぴり大変かもだけど、それが楽しいからいいの」"
  },
  {
    "name": "凪",
    "message": "「イヴがいいって言うなら俺は大歓迎だけど。\r\nなら明日も頼んでいいか？」"
  },
  {
    "name": "イヴ",
    "message": "「もちろん！　どんなのがいい？」"
  },
  {
    "name": "凪",
    "message": "「普通の弁当箱に入った弁当が食ってみたいんだよな。\r\n色々おかずが入ってるやつ」"
  },
  {
    "name": "イヴ",
    "message": "「へ、そんなのでいいの？」"
  },
  {
    "name": "凪",
    "message": "「こないだテレビで見て旨そうだったんだよなぁ。\r\nああいうの食ったことないしさ」"
  },
  {
    "name": "イヴ",
    "message": "「ぁ…………」"
  },
  {
    "name": "凪",
    "message": "「……って、イヴ？　どうした？」"
  },
  {
    "message": "気づけばイヴはどこか辛そうな顔をしていた。"
  },
  {
    "name": "凪",
    "message": "「やっぱり朝から品数が多いのは大変なのか？\r\n難しいなら無理しなくていいんだぞ？」"
  },
  {
    "message": "さっきまでの暗い表情が嘘だったかのように、\r\nイヴはパッと明るい笑顔を見せた。"
  },
  {
    "name": "イヴ",
    "message": "「まさか！　いいね、普通のお弁当。\r\nおかずは？　中身は何がいいの？」"
  },
  {
    "name": "凪",
    "message": "「どんな食いつきだよ。おかずは任せる。\r\nどういうものを入れるか知らないし」"
  },
  {
    "name": "イヴ",
    "message": "「わかった。っていうか、\r\n可能な限りは私が毎日凪のお弁当つくりたい！」"
  },
  {
    "name": "イヴ",
    "message": "「愛情たーっぷりいれるから。いいよね！」"
  },
  {
    "name": "凪",
    "message": "「俺は助かるけど……」"
  },
  {
    "name": "イヴ",
    "message": "「よし、決定！」"
  },
  {
    "message": "そんな会話をしているうちに\r\nサンドイッチは綺麗さっぱり姿を消した。"
  },
  {
    "name": "凪",
    "message": "「おかげさまで腹一杯だ。\r\n放課後まで頑張る気力も貰えた」"
  },
  {
    "name": "イヴ",
    "message": "「満足してもらえて安心したよ」"
  },
  {
    "message": "イヴが用意してくれたお茶を飲みながら、\r\nまったりと残りの時間を過ごす。"
  },
  {
    "message": "澄み渡る青い空。隣には料理上手な上に\r\n学園最強の彼女がここまで慕ってくれている。"
  },
  {
    "message": "なんていうんだろうなー。\r\nもうこういう気持ちを言葉で表すなら……。"
  },
  {
    "name": "凪",
    "message": "「幸せだなー」"
  },
  {
    "name": "イヴ",
    "message": "「…………っ！」"
  },
  {
    "name": "イヴ",
    "message": "「……まだまだ幸せになるよ。\r\nううん、私がしてみせる！」"
  },
  {
    "name": "凪",
    "message": "「じゃあ俺はイヴに返してやらないとな。\r\nそうすればお互いにずっと幸せで居続けられる」"
  },
  {
    "name": "イヴ",
    "message": "「そういうのいいね。\r\n明日も明後日も、来月も再来月もいつまでもね」"
  },
  {
    "message": "イヴも俺と同じく日光を遮るように手をかざしながら\r\n空を見上げる。"
  },
  {
    "name": "凪",
    "message": "「そういえばイヴ、次の休みの予定は？\r\n連休だしさ。よかったら一緒に過ごさないか？」"
  },
  {
    "name": "イヴ",
    "message": "「えっ、それはもちろん……。\r\nあっ、ううん。やっぱりやめておくっ！」"
  },
  {
    "name": "凪",
    "message": "「なんだ、用事でもあるのか？」"
  },
  {
    "name": "イヴ",
    "message": "「そんなところかなっ。\r\n凪はずっとお部屋にいるの？」"
  },
  {
    "name": "凪",
    "message": "「残念だけどそうなりそうだな」"
  },
  {
    "name": "イヴ",
    "message": "「そっかそっか。わかった。\r\nもし予定が変わったら教えてね！」"
  },
  {
    "name": "凪",
    "message": "「変わるもなにも、何もないんだが」"
  },
  {
    "name": "イヴ",
    "message": "「そうじゃなくて、ちょっと出かけるーとか、\r\nもしも予定が入ったら教えてほしいの」"
  },
  {
    "name": "凪",
    "message": "「いいけど、変わらないと思うぞ？\r\n最近はトウリもくくると遊んでばかりだし……」"
  },
  {
    "name": "イヴ",
    "message": "「そっか、それなら安心……、じゃなかった。\r\nお兄ちゃんとしてはちょっと寂しいね」"
  },
  {
    "name": "凪",
    "message": "「兄離れできてるのはいいことなんだが……」"
  },
  {
    "name": "イヴ",
    "message": "「私は一人っ子だけど、そういうのわかる気がするな」"
  },
  {
    "name": "イヴ",
    "message": "「汐莉のこととかも……わかってるつもりだったのに、\r\nわかってなかったみたいだし」"
  },
  {
    "name": "イヴ",
    "message": "「でも、諦めてはいないんだ。\r\nあの子が話す気になってたら、そのうち……」"
  },
  {
    "name": "イヴ",
    "message": "「――はっ！　ご、ごめん！\r\nちょっと湿っぽくなっちゃった」"
  },
  {
    "name": "凪",
    "message": "「なんで謝るんだよ。\r\n大切な話だし、聞けて良かった」"
  },
  {
    "name": "イヴ",
    "message": "「凪……。\r\n私、凪のそういうところだーいすきっ！」"
  },
  {
    "message": "隣に座っているイヴがぴったりと身体を預け、\r\n腕を組んでくる。"
  },
  {
    "name": "凪",
    "message": "「どわっ！？　ここでくっつくのはダメだろ！」"
  },
  {
    "name": "イヴ",
    "message": "「いいのー。見せつけちゃうのー」"
  },
  {
    "name": "凪",
    "message": "「まったく……」"
  },
  {
    "message": "口ではそう言っても、イヴが甘えてくるのが嬉しくて、\r\n結局そのまま許してしまう。"
  },
  {
    "name": "イヴ",
    "message": "「えへへへへ……」"
  },
  {
    "message": "それから昼休みが終わるまで、\r\n俺たちは周囲にバカップルぶりを見せつけたのだった。"
  },
  {
    "message": "そして、連休がやってきた。"
  },
  {
    "message": "せっかくだしどこかに出かけようと\r\n制服を着てみるも動く気になれない。"
  },
  {
    "message": "ベッドの上に寝転がってイヴとの毎日を思い返す。"
  },
  {
    "name": "凪",
    "message": "「まさか俺がこんな風に日々を\r\n噛みしめるようになるとは……」"
  },
  {
    "message": "恋人の存在は偉大だ。"
  },
  {
    "message": "そしてこの過程をすっとばして\r\nプロポーズしていた俺はなんて愚かだったんだ……。"
  },
  {
    "message": "あのときイヴが告白してくれなかったら、\r\n恋の楽しさに気づくことはなかったかもしれない。"
  },
  {
    "name": "凪",
    "message": "「イヴ……なにしてんのかな」"
  },
  {
    "message": "連絡してみようか。\r\nいや、用事があるのなら迷惑かもしれない。"
  },
  {
    "message": "うだうだと悩んでいると、不意に腹の音が鳴った。"
  },
  {
    "message": "時計を見れば、もう昼だ。"
  },
  {
    "message": "朝食もとっていないし、\r\nそろそろ食堂にでもいくか……。"
  },
  {
    "message": "起き上がると見計らったかのように、\r\n誰かがドアをノックする。"
  },
  {
    "message": "この時間ならテイオーか？"
  },
  {
    "name": "凪",
    "message": "「はーい」"
  },
  {
    "message": "ドアを開ける。そこには……。"
  },
  {
    "name": "イヴ",
    "message": "「あれ？　制服着てる……。\r\nもしかして出かけるところだった？」"
  },
  {
    "name": "凪",
    "message": "「イヴ！？　どうしたんだよ。\r\nなんかあったのか？」"
  },
  {
    "name": "イヴ",
    "message": "「違うよ。今日はサプライズ訪問！\r\n凪のために、お昼ご飯を作ってきました」"
  },
  {
    "message": "見ればイヴは大きな紙袋を持っている。"
  },
  {
    "name": "凪",
    "message": "「あれ、じゃあ用事って……」"
  },
  {
    "name": "イヴ",
    "message": "「ごめんねー、半分くらいは嘘でした」"
  },
  {
    "name": "イヴ",
    "message": "「運動部エリアで朝の鍛錬はしてきたんだけど、\r\n他に予定はなかったんだよね」"
  },
  {
    "name": "イヴ",
    "message": "「凪はもう予定とか入れちゃってた？\r\nもしかして私、ちゃんと聞いてなかった？」"
  },
  {
    "name": "凪",
    "message": "「いや、食堂に行こうとしてただけで、なにもない」"
  },
  {
    "name": "凪",
    "message": "「つーか、さっきまでイヴのこと考えてて……、\r\n特に用もないのに連絡しようか迷ってた」"
  },
  {
    "name": "イヴ",
    "message": "「えっ！？\r\nうぅっ……、私の恋人が素敵すぎる！」"
  },
  {
    "name": "イヴ",
    "message": "「せっかくだし、\r\n連絡もらってから来ればよかったな～」"
  },
  {
    "name": "凪",
    "message": "「まったく……。ほら、可愛い恋人さん、\r\nここじゃ目立つし、とりあえず中に入ってくれ」"
  },
  {
    "name": "イヴ",
    "message": "「お邪魔しまーす。\r\nすぐに用意しちゃっていいかな？」"
  },
  {
    "name": "凪",
    "message": "「ああ。腹ペコだ」"
  },
  {
    "name": "イヴ",
    "message": "「ナイスタイミングだったね」"
  },
  {
    "message": "イヴはタッパーを取り出し、蓋を外していく。"
  },
  {
    "message": "おにぎりにサラダ。\r\nウインナーに、ハンバーグ、から揚げ……。"
  },
  {
    "name": "凪",
    "message": "「豪勢だな。\r\n漫画とかで見る誕生日みたいだ」"
  },
  {
    "name": "イヴ",
    "message": "「張り切っちゃいました。\r\n基本はお弁当おかずの定番たち」"
  },
  {
    "name": "イヴ",
    "message": "「で、本命がこちらっ！」"
  },
  {
    "name": "イヴ",
    "message": "「蓼科シェフ特製、スタミナチキンだよ」"
  },
  {
    "name": "凪",
    "message": "「これは美味そうだな！\r\nこの匂いは空腹にきく……もう食べてもいいか？」"
  },
  {
    "name": "イヴ",
    "message": "「もちろん！　たくさん食べてね」"
  },
  {
    "message": "欲求のままに一口含んで咀嚼すると\r\nにんにくの香りが口の中に広がった。"
  },
  {
    "name": "凪",
    "message": "「…………」"
  },
  {
    "name": "イヴ",
    "message": "「なんだか、難しい顔だね。\r\nもしかして口に合わなかった？」"
  },
  {
    "name": "凪",
    "message": "「いや、味は文句のつけようがないんだけどさ……\r\nこれ、かなりニンニクが効いてるな」"
  },
  {
    "name": "イヴ",
    "message": "「えっ、ごめん。もしかして苦手だった？」"
  },
  {
    "name": "凪",
    "message": "「いや、そうじゃなくて」"
  },
  {
    "name": "イヴ",
    "message": "「じゃあなに？」"
  },
  {
    "name": "凪",
    "message": "「……このあといちゃつきたいと思ってたのに、\r\n匂いのせいでイヴが嫌がらないかなーと心配になった」"
  },
  {
    "name": "イヴ",
    "message": "「あははっ、凪ってば可愛すぎ！」"
  },
  {
    "name": "イヴ",
    "message": "「私も食べるし平気だよ。\r\nそれに相手が凪なら匂いなんて気にならない」"
  },
  {
    "message": "イヴがゆっくり顔を近づけてきてキスを一つ。"
  },
  {
    "message": "匂いを確かめるためなのか、\r\n本番さながらに舌を絡ませてきた。"
  },
  {
    "name": "イヴ",
    "message": "「うん、全然大丈夫」"
  },
  {
    "name": "イヴ",
    "message": "「というかね、ニンニクはわざとだったり」"
  },
  {
    "name": "イヴ",
    "message": "「凪にはしっかり食べて\r\nスタミナをつけてもらいたかったの」"
  },
  {
    "name": "イヴ",
    "message": "「せっかくの連休だし、\r\n凪さえ嫌じゃなかったらその……」"
  },
  {
    "name": "イヴ",
    "message": "「前のデートの最後と同じことをしたいなぁ、\r\nなんて……。それでね、思ったの」"
  },
  {
    "name": "イヴ",
    "message": "「体力の面だとどうしても私のほうが優れてるし、\r\n凪が途中でバテないようにしたほうがいいなって」"
  },
  {
    "message": "率直なお誘いに、思わず箸を落とす。"
  },
  {
    "name": "イヴ",
    "message": "「えっ、あれ？　凪はしたくなかった！？」"
  },
  {
    "name": "凪",
    "message": "「いや、したかったよ。\r\n考えないわけがないんだが……」"
  },
  {
    "name": "凪",
    "message": "「イヴ、エロすぎないか？」"
  },
  {
    "name": "イヴ",
    "message": "「えぇっ、どこが！？」"
  },
  {
    "name": "凪",
    "message": "「いや、だってさ。さっきの発言を要約すると、\r\nイヴの体力が尽きるまでしたいってことだろ」"
  },
  {
    "name": "イヴ",
    "message": "「えっ？　それは……ええと……」"
  },
  {
    "name": "イヴ",
    "message": "「そういうことに、なるかな……」"
  },
  {
    "name": "イヴ",
    "message": "「ごめん、引いた？\r\n恋人がエッチに興味津々なの、嫌じゃない？」"
  },
  {
    "name": "凪",
    "message": "「まさか、嬉しいよ」"
  },
  {
    "name": "イヴ",
    "message": "「それならいいけど……」"
  },
  {
    "message": "顔を赤くしながらイヴは料理を口に運んだ。"
  },
  {
    "message": "俺も腹が減っているはずなのだが、\r\nどうしてもイヴのことを意識してしまう。"
  },
  {
    "message": "気づけば、どちらも箸を止めていた。"
  },
  {
    "name": "イヴ",
    "message": "「ねぇ、凪。\r\n私、食事より先にしたいことがあるんだけど……」"
  },
  {
    "name": "凪",
    "message": "「奇遇だな。俺も同じことを考えてた」"
  },
  {
    "message": "そのままもつれるように立ち上がり、\r\nベッドへと腰かける。"
  },
  {
    "name": "イヴ",
    "message": "「凪のもう勃っちゃってるね、\r\nこれはいつから？」"
  },
  {
    "name": "凪",
    "message": "「キスしてからずっとだな」"
  },
  {
    "name": "イヴ",
    "message": "「ふふっ、なら作戦成功だね」"
  },
  {
    "message": "そう言いながらイヴは俺の下半身へと\r\n手を伸ばした。"
  }
]